<?xml version="1.0" encoding="UTF-8"?><record_update sys_domain="global" table="sys_hub_flow">
    <sys_hub_flow action="DELETE">
        <access>public</access>
        <acls/>
        <active>true</active>
        <annotation/>
        <callable_by_client_api>false</callable_by_client_api>
        <category/>
        <compiler_build/>
        <copied_from/>
        <copied_from_name/>
        <description/>
        <internal_name>test_subflow_2</internal_name>
        <label_cache>[{"name":"1356c76a-ba69-4f7b-b5cb-c0fad77117ad.nonce","label":"2➛nonce","reference_display":"nonce","type":"string","base_type":"string","attributes":{"uiTypeLabel":"String","element_mapping_provider":"com.glide.flow_design.action.data.FlowDesignVariableMapper","pwd2droppable":"true","uiType":"string","uiUniqueId":"3ec58a30-47ed-400d-a21a-b8d88e078456"}},{"name":"subflow.account.key","label":"Input➛account➛Key","reference":"x_snc_ethsign_key","reference_display":"Key","type":"reference","base_type":"reference","parent_table_name":"x_snc_ethsign_account","column_name":"key"},{"name":"aece5707-e790-4ab3-87e5-338f0e5b9beb.endpoint","label":"1➛endpoint","reference":"x_snc_ethereum_endpoint","reference_display":"Endpoint","type":"reference","base_type":"reference","attributes":{"uiType":"reference","uiTypeLabel":"Reference","element_mapping_provider":"com.glide.flow_design.action.data.FlowDesignVariableMapper","uiUniqueId":"61dfb561-5b1a-4f4c-adc0-3f3c6e4f5997"}},{"name":"1f71ceb8-ee44-4e64-9f29-17a2928474ed.nonce","label":"2➛nonce","reference_display":"nonce","type":"string","base_type":"string","attributes":{"uiTypeLabel":"String","element_mapping_provider":"com.glide.flow_design.action.data.FlowDesignVariableMapper","pwd2droppable":"true","uiType":"string","uiUniqueId":"3ec58a30-47ed-400d-a21a-b8d88e078456"}},{"name":"subflow.network","label":"Input➛network","reference":"x_snc_ethereum_network","reference_display":"Network","type":"reference","base_type":"reference","attributes":{"sourceUiUniqueId":"","sourceType":"","sourceId":"","uiUniqueId":"3597a85b-fa8e-468d-a286-e2fcbb81eddf"}}]</label_cache>
        <latest_snapshot>0ebeb4bedb2c2010969430d868961914</latest_snapshot>
        <master_snapshot>0ebeb4bedb2c2010969430d868961914</master_snapshot>
        <name>Test Subflow 2</name>
        <natlang/>
        <outputs/>
        <remote_trigger_id/>
        <run_as>user</run_as>
        <sc_callable>false</sc_callable>
        <show_draft_actions>false</show_draft_actions>
        <show_triggered_flows>false</show_triggered_flows>
        <status>published</status>
        <sys_class_name>sys_hub_flow</sys_class_name>
        <sys_created_by>admin</sys_created_by>
        <sys_created_on>2020-11-21 17:23:56</sys_created_on>
        <sys_domain>global</sys_domain>
        <sys_domain_path>/</sys_domain_path>
        <sys_id>c57db47edb2c2010969430d8689619c7</sys_id>
        <sys_mod_count>10</sys_mod_count>
        <sys_name>Test Subflow 2</sys_name>
        <sys_overrides/>
        <sys_package display_value="Ethereum" source="x_snc_ethereum">3c0e4434db442010969430d868961918</sys_package>
        <sys_policy/>
        <sys_scope display_value="Ethereum">3c0e4434db442010969430d868961918</sys_scope>
        <sys_update_name>sys_hub_flow_c57db47edb2c2010969430d8689619c7</sys_update_name>
        <sys_updated_by>admin</sys_updated_by>
        <sys_updated_on>2020-11-21 17:59:47</sys_updated_on>
        <type>subflow</type>
    </sys_hub_flow>
    <sys_translated_text action="DELETE" query="documentkey=c57db47edb2c2010969430d8689619c7"/>
    <sys_variable_value action="DELETE" query="document_key=c57db47edb2c2010969430d8689619c7"/>
    <sys_hub_flow_component action="DELETE" query="flow=c57db47edb2c2010969430d8689619c7^sys_idNOT IN7f954536db6c2010969430d8689619db,a3ed3c7edb2c2010969430d868961962"/>
    <sys_hub_action_instance action="DELETE">
        <action_inputs/>
        <action_inputs/>
        <action_type display_value="Copy of Define Nonce">a8658136db6c2010969430d868961966</action_type>
        <action_type_parent/>
        <comment/>
        <compiled_snapshot/>
        <display_text/>
        <flow display_value="Test Subflow 2">c57db47edb2c2010969430d8689619c7</flow>
        <order>2</order>
        <parent_ui_id/>
        <sys_class_name>sys_hub_action_instance</sys_class_name>
        <sys_created_by>admin</sys_created_by>
        <sys_created_on>2020-11-21 17:59:38</sys_created_on>
        <sys_id>7f954536db6c2010969430d8689619db</sys_id>
        <sys_mod_count>6</sys_mod_count>
        <sys_scope display_value="Ethereum">3c0e4434db442010969430d868961918</sys_scope>
        <sys_updated_by>admin</sys_updated_by>
        <sys_updated_on>2020-11-21 17:59:47</sys_updated_on>
        <ui_id>1356c76a-ba69-4f7b-b5cb-c0fad77117ad</ui_id>
    </sys_hub_action_instance>
    <sys_variable_value action="DELETE" query="document_key=7f954536db6c2010969430d8689619db"/>
    <sys_element_mapping action="DELETE" query="id=7f954536db6c2010969430d8689619db"/>
    <sys_element_mapping action="DELETE">
        <field>endpoint</field>
        <id>7f954536db6c2010969430d8689619db</id>
        <sys_created_by>admin</sys_created_by>
        <sys_created_on>2020-11-21 17:59:38</sys_created_on>
        <sys_id>f7954536db6c2010969430d8689619dd</sys_id>
        <sys_mod_count>0</sys_mod_count>
        <sys_updated_by>admin</sys_updated_by>
        <sys_updated_on>2020-11-21 17:59:38</sys_updated_on>
        <table>var__m_sys_hub_action_input_a8658136db6c2010969430d868961966</table>
        <value>{{aece5707-e790-4ab3-87e5-338f0e5b9beb.endpoint}}</value>
    </sys_element_mapping>
    <sys_element_mapping action="DELETE">
        <field>key</field>
        <id>7f954536db6c2010969430d8689619db</id>
        <sys_created_by>admin</sys_created_by>
        <sys_created_on>2020-11-21 17:59:38</sys_created_on>
        <sys_id>bb954536db6c2010969430d8689619dd</sys_id>
        <sys_mod_count>0</sys_mod_count>
        <sys_updated_by>admin</sys_updated_by>
        <sys_updated_on>2020-11-21 17:59:38</sys_updated_on>
        <table>var__m_sys_hub_action_input_a8658136db6c2010969430d868961966</table>
        <value>{{subflow.account.key}}</value>
    </sys_element_mapping>
    <sys_hub_action_instance action="DELETE">
        <action_inputs/>
        <action_inputs/>
        <action_type display_value="Identify Endpoint">1643eb16db602010969430d868961947</action_type>
        <action_type_parent/>
        <comment/>
        <compiled_snapshot/>
        <display_text/>
        <flow display_value="Test Subflow 2">c57db47edb2c2010969430d8689619c7</flow>
        <order>1</order>
        <parent_ui_id/>
        <sys_class_name>sys_hub_action_instance</sys_class_name>
        <sys_created_by>admin</sys_created_by>
        <sys_created_on>2020-11-21 17:26:02</sys_created_on>
        <sys_id>a3ed3c7edb2c2010969430d868961962</sys_id>
        <sys_mod_count>20</sys_mod_count>
        <sys_scope display_value="Ethereum">3c0e4434db442010969430d868961918</sys_scope>
        <sys_updated_by>admin</sys_updated_by>
        <sys_updated_on>2020-11-21 17:59:47</sys_updated_on>
        <ui_id>aece5707-e790-4ab3-87e5-338f0e5b9beb</ui_id>
    </sys_hub_action_instance>
    <sys_variable_value action="DELETE" query="document_key=a3ed3c7edb2c2010969430d868961962"/>
    <sys_element_mapping action="DELETE" query="id=a3ed3c7edb2c2010969430d868961962"/>
    <sys_element_mapping action="DELETE">
        <field>network</field>
        <id>a3ed3c7edb2c2010969430d868961962</id>
        <sys_created_by>admin</sys_created_by>
        <sys_created_on>2020-11-21 17:26:02</sys_created_on>
        <sys_id>6fed3c7edb2c2010969430d868961963</sys_id>
        <sys_mod_count>0</sys_mod_count>
        <sys_updated_by>admin</sys_updated_by>
        <sys_updated_on>2020-11-21 17:26:02</sys_updated_on>
        <table>var__m_sys_hub_action_input_1643eb16db602010969430d868961947</table>
        <value>{{subflow.network}}</value>
    </sys_element_mapping>
    <sys_flow_cat_variable_model action="DELETE" query="id=c57db47edb2c2010969430d8689619c7^sys_idNOT IN8d7db47edb2c2010969430d8689619c9"/>
    <sys_flow_cat_variable_model action="DELETE">
        <id>c57db47edb2c2010969430d8689619c7</id>
        <name>Test Subflow 2</name>
        <sys_created_by>admin</sys_created_by>
        <sys_created_on>2020-11-21 17:23:56</sys_created_on>
        <sys_id>8d7db47edb2c2010969430d8689619c9</sys_id>
        <sys_mod_count>0</sys_mod_count>
        <sys_scope/>
        <sys_updated_by>admin</sys_updated_by>
        <sys_updated_on>2020-11-21 17:23:56</sys_updated_on>
    </sys_flow_cat_variable_model>
    <sys_hub_flow_input action="DELETE" query="model=c57db47edb2c2010969430d8689619c7^sys_idNOT IN0f92c172db6c2010969430d868961918,67edb87edb2c2010969430d868961948"/>
    <sys_hub_flow_input action="DELETE">
        <active>true</active>
        <array>false</array>
        <array_denormalized>false</array_denormalized>
        <attributes>element_mapping_provider=com.glide.flow_design.action.data.FlowDesignVariableMapper,uiType=reference,uiTypeLabel=Reference,uiUniqueId=8bc7b41a-4665-4dad-8beb-e207993798f2</attributes>
        <audit>false</audit>
        <calculation><![CDATA[(function calculatedFieldValue(current) {

	// Add your code here
	return '';  // return the calculated value

})(current);]]></calculation>
        <choice/>
        <choice_field/>
        <choice_table>x_snc_ethsign_account</choice_table>
        <column_label/>
        <comments/>
        <create_roles/>
        <default_value/>
        <defaultsort/>
        <delete_roles/>
        <dependent/>
        <dependent_on_field/>
        <display>false</display>
        <dynamic_creation>false</dynamic_creation>
        <dynamic_creation_script/>
        <dynamic_default_value/>
        <dynamic_ref_qual/>
        <element>account</element>
        <element_reference>false</element_reference>
        <foreign_database/>
        <function_definition/>
        <function_field>false</function_field>
        <help/>
        <hint/>
        <internal_type display_value="Reference">reference</internal_type>
        <label>account</label>
        <mandatory>true</mandatory>
        <max_length>32</max_length>
        <model display_value="Test Subflow 2">c57db47edb2c2010969430d8689619c7</model>
        <model_id>c57db47edb2c2010969430d8689619c7</model_id>
        <model_table>sys_hub_flow</model_table>
        <name>var__m_sys_hub_flow_input_c57db47edb2c2010969430d8689619c7</name>
        <next_element/>
        <order>2</order>
        <primary>false</primary>
        <read_only>false</read_only>
        <read_roles/>
        <reference display_value="" name="x_snc_ethsign_account">x_snc_ethsign_account</reference>
        <reference_cascade_rule/>
        <reference_floats>false</reference_floats>
        <reference_key/>
        <reference_qual/>
        <reference_qual_condition/>
        <reference_type/>
        <sizeclass/>
        <spell_check>false</spell_check>
        <staged>false</staged>
        <sys_class_name>sys_hub_flow_input</sys_class_name>
        <sys_created_by>admin</sys_created_by>
        <sys_created_on>2020-11-21 17:46:28</sys_created_on>
        <sys_id>0f92c172db6c2010969430d868961918</sys_id>
        <sys_mod_count>1</sys_mod_count>
        <sys_name/>
        <sys_package/>
        <sys_policy/>
        <sys_scope display_value="Ethereum">3c0e4434db442010969430d868961918</sys_scope>
        <sys_update_name/>
        <sys_updated_by>admin</sys_updated_by>
        <sys_updated_on>2020-11-21 17:46:28</sys_updated_on>
        <table_reference>false</table_reference>
        <text_index>false</text_index>
        <unique>false</unique>
        <use_dependent_field>false</use_dependent_field>
        <use_dynamic_default>false</use_dynamic_default>
        <use_reference_qualifier>simple</use_reference_qualifier>
        <virtual>false</virtual>
        <widget/>
        <write_roles/>
        <xml_view>false</xml_view>
    </sys_hub_flow_input>
    <sys_hub_flow_input action="DELETE">
        <active>true</active>
        <array>false</array>
        <array_denormalized>false</array_denormalized>
        <attributes>element_mapping_provider=com.glide.flow_design.action.data.FlowDesignVariableMapper,uiType=reference,uiTypeLabel=Reference,uiUniqueId=3597a85b-fa8e-468d-a286-e2fcbb81eddf</attributes>
        <audit>false</audit>
        <calculation><![CDATA[(function calculatedFieldValue(current) {

	// Add your code here
	return '';  // return the calculated value

})(current);]]></calculation>
        <choice/>
        <choice_field/>
        <choice_table>x_snc_ethereum_network</choice_table>
        <column_label/>
        <comments/>
        <create_roles/>
        <default_value/>
        <defaultsort/>
        <delete_roles/>
        <dependent/>
        <dependent_on_field/>
        <display>false</display>
        <dynamic_creation>false</dynamic_creation>
        <dynamic_creation_script/>
        <dynamic_default_value/>
        <dynamic_ref_qual/>
        <element>network</element>
        <element_reference>false</element_reference>
        <foreign_database/>
        <function_definition/>
        <function_field>false</function_field>
        <help/>
        <hint/>
        <internal_type display_value="Reference">reference</internal_type>
        <label>network</label>
        <mandatory>true</mandatory>
        <max_length>32</max_length>
        <model display_value="Test Subflow 2">c57db47edb2c2010969430d8689619c7</model>
        <model_id>c57db47edb2c2010969430d8689619c7</model_id>
        <model_table>sys_hub_flow</model_table>
        <name>var__m_sys_hub_flow_input_c57db47edb2c2010969430d8689619c7</name>
        <next_element/>
        <order>1</order>
        <primary>false</primary>
        <read_only>false</read_only>
        <read_roles/>
        <reference display_value="" name="x_snc_ethereum_network">x_snc_ethereum_network</reference>
        <reference_cascade_rule/>
        <reference_floats>false</reference_floats>
        <reference_key/>
        <reference_qual/>
        <reference_qual_condition/>
        <reference_type/>
        <sizeclass/>
        <spell_check>false</spell_check>
        <staged>false</staged>
        <sys_class_name>sys_hub_flow_input</sys_class_name>
        <sys_created_by>admin</sys_created_by>
        <sys_created_on>2020-11-21 17:26:01</sys_created_on>
        <sys_id>67edb87edb2c2010969430d868961948</sys_id>
        <sys_mod_count>1</sys_mod_count>
        <sys_name/>
        <sys_package/>
        <sys_policy/>
        <sys_scope display_value="Ethereum">3c0e4434db442010969430d868961918</sys_scope>
        <sys_update_name/>
        <sys_updated_by>admin</sys_updated_by>
        <sys_updated_on>2020-11-21 17:26:02</sys_updated_on>
        <table_reference>false</table_reference>
        <text_index>false</text_index>
        <unique>false</unique>
        <use_dependent_field>false</use_dependent_field>
        <use_dynamic_default>false</use_dynamic_default>
        <use_reference_qualifier>simple</use_reference_qualifier>
        <virtual>false</virtual>
        <widget/>
        <write_roles/>
        <xml_view>false</xml_view>
    </sys_hub_flow_input>
    <sys_hub_action_instance action="DELETE" query="flow=c57db47edb2c2010969430d8689619c7^sys_idNOT IN7f954536db6c2010969430d8689619db,a3ed3c7edb2c2010969430d868961962"/>
    <sys_hub_action_instance action="DELETE">
        <action_inputs/>
        <action_inputs/>
        <action_type display_value="Copy of Define Nonce">a8658136db6c2010969430d868961966</action_type>
        <action_type_parent/>
        <comment/>
        <compiled_snapshot/>
        <display_text/>
        <flow display_value="Test Subflow 2">c57db47edb2c2010969430d8689619c7</flow>
        <order>2</order>
        <parent_ui_id/>
        <sys_class_name>sys_hub_action_instance</sys_class_name>
        <sys_created_by>admin</sys_created_by>
        <sys_created_on>2020-11-21 17:59:38</sys_created_on>
        <sys_id>7f954536db6c2010969430d8689619db</sys_id>
        <sys_mod_count>6</sys_mod_count>
        <sys_scope display_value="Ethereum">3c0e4434db442010969430d868961918</sys_scope>
        <sys_updated_by>admin</sys_updated_by>
        <sys_updated_on>2020-11-21 17:59:47</sys_updated_on>
        <ui_id>1356c76a-ba69-4f7b-b5cb-c0fad77117ad</ui_id>
    </sys_hub_action_instance>
    <sys_variable_value action="DELETE" query="document_key=7f954536db6c2010969430d8689619db"/>
    <sys_element_mapping action="DELETE" query="id=7f954536db6c2010969430d8689619db"/>
    <sys_element_mapping action="DELETE">
        <field>endpoint</field>
        <id>7f954536db6c2010969430d8689619db</id>
        <sys_created_by>admin</sys_created_by>
        <sys_created_on>2020-11-21 17:59:38</sys_created_on>
        <sys_id>f7954536db6c2010969430d8689619dd</sys_id>
        <sys_mod_count>0</sys_mod_count>
        <sys_updated_by>admin</sys_updated_by>
        <sys_updated_on>2020-11-21 17:59:38</sys_updated_on>
        <table>var__m_sys_hub_action_input_a8658136db6c2010969430d868961966</table>
        <value>{{aece5707-e790-4ab3-87e5-338f0e5b9beb.endpoint}}</value>
    </sys_element_mapping>
    <sys_element_mapping action="DELETE">
        <field>key</field>
        <id>7f954536db6c2010969430d8689619db</id>
        <sys_created_by>admin</sys_created_by>
        <sys_created_on>2020-11-21 17:59:38</sys_created_on>
        <sys_id>bb954536db6c2010969430d8689619dd</sys_id>
        <sys_mod_count>0</sys_mod_count>
        <sys_updated_by>admin</sys_updated_by>
        <sys_updated_on>2020-11-21 17:59:38</sys_updated_on>
        <table>var__m_sys_hub_action_input_a8658136db6c2010969430d868961966</table>
        <value>{{subflow.account.key}}</value>
    </sys_element_mapping>
    <sys_hub_action_instance action="DELETE">
        <action_inputs/>
        <action_inputs/>
        <action_type display_value="Identify Endpoint">1643eb16db602010969430d868961947</action_type>
        <action_type_parent/>
        <comment/>
        <compiled_snapshot/>
        <display_text/>
        <flow display_value="Test Subflow 2">c57db47edb2c2010969430d8689619c7</flow>
        <order>1</order>
        <parent_ui_id/>
        <sys_class_name>sys_hub_action_instance</sys_class_name>
        <sys_created_by>admin</sys_created_by>
        <sys_created_on>2020-11-21 17:26:02</sys_created_on>
        <sys_id>a3ed3c7edb2c2010969430d868961962</sys_id>
        <sys_mod_count>20</sys_mod_count>
        <sys_scope display_value="Ethereum">3c0e4434db442010969430d868961918</sys_scope>
        <sys_updated_by>admin</sys_updated_by>
        <sys_updated_on>2020-11-21 17:59:47</sys_updated_on>
        <ui_id>aece5707-e790-4ab3-87e5-338f0e5b9beb</ui_id>
    </sys_hub_action_instance>
    <sys_variable_value action="DELETE" query="document_key=a3ed3c7edb2c2010969430d868961962"/>
    <sys_element_mapping action="DELETE" query="id=a3ed3c7edb2c2010969430d868961962"/>
    <sys_element_mapping action="DELETE">
        <field>network</field>
        <id>a3ed3c7edb2c2010969430d868961962</id>
        <sys_created_by>admin</sys_created_by>
        <sys_created_on>2020-11-21 17:26:02</sys_created_on>
        <sys_id>6fed3c7edb2c2010969430d868961963</sys_id>
        <sys_mod_count>0</sys_mod_count>
        <sys_updated_by>admin</sys_updated_by>
        <sys_updated_on>2020-11-21 17:26:02</sys_updated_on>
        <table>var__m_sys_hub_action_input_1643eb16db602010969430d868961947</table>
        <value>{{subflow.network}}</value>
    </sys_element_mapping>
    <sys_documentation action="DELETE" query="name=var__m_sys_hub_flow_input_c57db47edb2c2010969430d8689619c7^sys_idNOT IN8f92c172db6c2010969430d86896191e,e7ed3c7edb2c2010969430d86896195c"/>
    <sys_documentation action="DELETE">
        <element>account</element>
        <help/>
        <hint/>
        <label>account</label>
        <language>en</language>
        <name>var__m_sys_hub_flow_input_c57db47edb2c2010969430d8689619c7</name>
        <plural/>
        <sys_class_name>sys_documentation</sys_class_name>
        <sys_created_by>admin</sys_created_by>
        <sys_created_on>2020-11-21 17:46:28</sys_created_on>
        <sys_id>8f92c172db6c2010969430d86896191e</sys_id>
        <sys_mod_count>0</sys_mod_count>
        <sys_name/>
        <sys_package display_value="Ethereum" source="x_snc_ethereum">3c0e4434db442010969430d868961918</sys_package>
        <sys_policy/>
        <sys_scope display_value="Ethereum">3c0e4434db442010969430d868961918</sys_scope>
        <sys_update_name/>
        <sys_updated_by>admin</sys_updated_by>
        <sys_updated_on>2020-11-21 17:46:28</sys_updated_on>
        <url/>
        <url_target/>
    </sys_documentation>
    <sys_documentation action="DELETE">
        <element>network</element>
        <help/>
        <hint/>
        <label>network</label>
        <language>en</language>
        <name>var__m_sys_hub_flow_input_c57db47edb2c2010969430d8689619c7</name>
        <plural/>
        <sys_class_name>sys_documentation</sys_class_name>
        <sys_created_by>admin</sys_created_by>
        <sys_created_on>2020-11-21 17:26:02</sys_created_on>
        <sys_id>e7ed3c7edb2c2010969430d86896195c</sys_id>
        <sys_mod_count>0</sys_mod_count>
        <sys_name/>
        <sys_package display_value="Ethereum" source="x_snc_ethereum">3c0e4434db442010969430d868961918</sys_package>
        <sys_policy/>
        <sys_scope display_value="Ethereum">3c0e4434db442010969430d868961918</sys_scope>
        <sys_update_name/>
        <sys_updated_by>admin</sys_updated_by>
        <sys_updated_on>2020-11-21 17:26:02</sys_updated_on>
        <url/>
        <url_target/>
    </sys_documentation>
    <sys_flow_subflow_plan action="DELETE" query="plan_id=c57db47edb2c2010969430d8689619c7^sys_idNOT INe2beb4bedb2c2010969430d868961976"/>
    <sys_flow_subflow_plan action="DELETE">
        <plan>com.snc.process_flow.engine.ProcessPlan@59f07a</plan>
        <plan_id display_value="Test Subflow 2">c57db47edb2c2010969430d8689619c7</plan_id>
        <snapshot>0ebeb4bedb2c2010969430d868961914</snapshot>
        <sys_created_by>admin</sys_created_by>
        <sys_created_on>2020-11-21 17:29:30</sys_created_on>
        <sys_domain>global</sys_domain>
        <sys_domain_path>/</sys_domain_path>
        <sys_id>e2beb4bedb2c2010969430d868961976</sys_id>
        <sys_mod_count>2</sys_mod_count>
        <sys_overrides/>
        <sys_scope/>
        <sys_updated_by>admin</sys_updated_by>
        <sys_updated_on>2020-11-21 17:59:47</sys_updated_on>
    </sys_flow_subflow_plan>
    <sys_hub_flow_snapshot action="DELETE">
        <access>public</access>
        <acls/>
        <active>true</active>
        <annotation/>
        <callable_by_client_api>false</callable_by_client_api>
        <category/>
        <copied_from/>
        <copied_from_name/>
        <description/>
        <internal_name>test_subflow_2</internal_name>
        <label_cache>[{"name":"1356c76a-ba69-4f7b-b5cb-c0fad77117ad.nonce","label":"2➛nonce","reference_display":"nonce","type":"string","base_type":"string","attributes":{"uiTypeLabel":"String","element_mapping_provider":"com.glide.flow_design.action.data.FlowDesignVariableMapper","pwd2droppable":"true","uiType":"string","uiUniqueId":"3ec58a30-47ed-400d-a21a-b8d88e078456"}},{"name":"subflow.account.key","label":"Input➛account➛Key","reference":"x_snc_ethsign_key","reference_display":"Key","type":"reference","base_type":"reference","parent_table_name":"x_snc_ethsign_account","column_name":"key"},{"name":"aece5707-e790-4ab3-87e5-338f0e5b9beb.endpoint","label":"1➛endpoint","reference":"x_snc_ethereum_endpoint","reference_display":"Endpoint","type":"reference","base_type":"reference","attributes":{"uiType":"reference","uiTypeLabel":"Reference","element_mapping_provider":"com.glide.flow_design.action.data.FlowDesignVariableMapper","uiUniqueId":"61dfb561-5b1a-4f4c-adc0-3f3c6e4f5997"}},{"name":"1f71ceb8-ee44-4e64-9f29-17a2928474ed.nonce","label":"2➛nonce","reference_display":"nonce","type":"string","base_type":"string","attributes":{"uiTypeLabel":"String","element_mapping_provider":"com.glide.flow_design.action.data.FlowDesignVariableMapper","pwd2droppable":"true","uiType":"string","uiUniqueId":"3ec58a30-47ed-400d-a21a-b8d88e078456"}},{"name":"subflow.network","label":"Input➛network","reference":"x_snc_ethereum_network","reference_display":"Network","type":"reference","base_type":"reference","attributes":{"sourceUiUniqueId":"","sourceType":"","sourceId":"","uiUniqueId":"3597a85b-fa8e-468d-a286-e2fcbb81eddf"}}]</label_cache>
        <master>true</master>
        <name>Test Subflow 2</name>
        <natlang/>
        <outputs/>
        <parent_flow display_value="Test Subflow 2">c57db47edb2c2010969430d8689619c7</parent_flow>
        <remote_trigger_id/>
        <run_as>user</run_as>
        <sc_callable>false</sc_callable>
        <status>published</status>
        <sys_class_name>sys_hub_flow_snapshot</sys_class_name>
        <sys_created_by>admin</sys_created_by>
        <sys_created_on>2020-11-21 17:29:29</sys_created_on>
        <sys_domain>global</sys_domain>
        <sys_domain_path>/</sys_domain_path>
        <sys_id>0ebeb4bedb2c2010969430d868961914</sys_id>
        <sys_mod_count>2</sys_mod_count>
        <sys_name/>
        <sys_overrides/>
        <sys_package/>
        <sys_policy/>
        <sys_scope display_value="Ethereum">3c0e4434db442010969430d868961918</sys_scope>
        <sys_update_name/>
        <sys_updated_by>admin</sys_updated_by>
        <sys_updated_on>2020-11-21 17:59:46</sys_updated_on>
        <type>subflow</type>
    </sys_hub_flow_snapshot>
    <sys_translated_text action="DELETE" query="documentkey=0ebeb4bedb2c2010969430d868961914"/>
    <sys_variable_value action="DELETE" query="document_key=0ebeb4bedb2c2010969430d868961914"/>
    <sys_hub_flow_component action="DELETE" query="flow=0ebeb4bedb2c2010969430d868961914^sys_idNOT IN16beb4bedb2c2010969430d868961932,b9a58536db6c2010969430d86896198c"/>
    <sys_hub_action_instance action="DELETE">
        <action_inputs/>
        <action_inputs/>
        <action_type display_value="Identify Endpoint">1643eb16db602010969430d868961947</action_type>
        <action_type_parent display_value="Identify Endpoint">07b22716db602010969430d868961946</action_type_parent>
        <comment/>
        <compiled_snapshot>1643eb16db602010969430d868961947</compiled_snapshot>
        <display_text/>
        <flow display_value="Test Subflow 2">0ebeb4bedb2c2010969430d868961914</flow>
        <order>1</order>
        <parent_ui_id/>
        <sys_class_name>sys_hub_action_instance</sys_class_name>
        <sys_created_by>admin</sys_created_by>
        <sys_created_on>2020-11-21 17:29:29</sys_created_on>
        <sys_id>16beb4bedb2c2010969430d868961932</sys_id>
        <sys_mod_count>10</sys_mod_count>
        <sys_scope display_value="Ethereum">3c0e4434db442010969430d868961918</sys_scope>
        <sys_updated_by>admin</sys_updated_by>
        <sys_updated_on>2020-11-21 17:59:46</sys_updated_on>
        <ui_id>aece5707-e790-4ab3-87e5-338f0e5b9beb</ui_id>
    </sys_hub_action_instance>
    <sys_variable_value action="DELETE" query="document_key=16beb4bedb2c2010969430d868961932"/>
    <sys_element_mapping action="DELETE" query="id=16beb4bedb2c2010969430d868961932"/>
    <sys_element_mapping action="DELETE">
        <field>network</field>
        <id>16beb4bedb2c2010969430d868961932</id>
        <sys_created_by>admin</sys_created_by>
        <sys_created_on>2020-11-21 17:29:29</sys_created_on>
        <sys_id>52beb4bedb2c2010969430d868961933</sys_id>
        <sys_mod_count>0</sys_mod_count>
        <sys_updated_by>admin</sys_updated_by>
        <sys_updated_on>2020-11-21 17:29:29</sys_updated_on>
        <table>var__m_sys_hub_action_input_1643eb16db602010969430d868961947</table>
        <value>{{subflow.network}}</value>
    </sys_element_mapping>
    <sys_hub_action_instance action="DELETE">
        <action_inputs/>
        <action_inputs/>
        <action_type display_value="Copy of Define Nonce">a8658136db6c2010969430d868961966</action_type>
        <action_type_parent display_value="Copy of Define Nonce">8345cdf2db6c2010969430d8689619d9</action_type_parent>
        <comment/>
        <compiled_snapshot>a8658136db6c2010969430d868961966</compiled_snapshot>
        <display_text/>
        <flow display_value="Test Subflow 2">0ebeb4bedb2c2010969430d868961914</flow>
        <order>2</order>
        <parent_ui_id/>
        <sys_class_name>sys_hub_action_instance</sys_class_name>
        <sys_created_by>admin</sys_created_by>
        <sys_created_on>2020-11-21 17:59:46</sys_created_on>
        <sys_id>b9a58536db6c2010969430d86896198c</sys_id>
        <sys_mod_count>4</sys_mod_count>
        <sys_scope display_value="Ethereum">3c0e4434db442010969430d868961918</sys_scope>
        <sys_updated_by>admin</sys_updated_by>
        <sys_updated_on>2020-11-21 17:59:46</sys_updated_on>
        <ui_id>1356c76a-ba69-4f7b-b5cb-c0fad77117ad</ui_id>
    </sys_hub_action_instance>
    <sys_variable_value action="DELETE" query="document_key=b9a58536db6c2010969430d86896198c"/>
    <sys_element_mapping action="DELETE" query="id=b9a58536db6c2010969430d86896198c"/>
    <sys_element_mapping action="DELETE">
        <field>endpoint</field>
        <id>b9a58536db6c2010969430d86896198c</id>
        <sys_created_by>admin</sys_created_by>
        <sys_created_on>2020-11-21 17:59:46</sys_created_on>
        <sys_id>79a58536db6c2010969430d86896198d</sys_id>
        <sys_mod_count>0</sys_mod_count>
        <sys_updated_by>admin</sys_updated_by>
        <sys_updated_on>2020-11-21 17:59:46</sys_updated_on>
        <table>var__m_sys_hub_action_input_a8658136db6c2010969430d868961966</table>
        <value>{{aece5707-e790-4ab3-87e5-338f0e5b9beb.endpoint}}</value>
    </sys_element_mapping>
    <sys_element_mapping action="DELETE">
        <field>key</field>
        <id>b9a58536db6c2010969430d86896198c</id>
        <sys_created_by>admin</sys_created_by>
        <sys_created_on>2020-11-21 17:59:46</sys_created_on>
        <sys_id>3da58536db6c2010969430d86896198d</sys_id>
        <sys_mod_count>0</sys_mod_count>
        <sys_updated_by>admin</sys_updated_by>
        <sys_updated_on>2020-11-21 17:59:46</sys_updated_on>
        <table>var__m_sys_hub_action_input_a8658136db6c2010969430d868961966</table>
        <value>{{subflow.account.key}}</value>
    </sys_element_mapping>
    <sys_flow_cat_variable_model action="DELETE" query="id=0ebeb4bedb2c2010969430d868961914^sys_idNOT IN02beb4bedb2c2010969430d868961915"/>
    <sys_flow_cat_variable_model action="DELETE">
        <id>0ebeb4bedb2c2010969430d868961914</id>
        <name>Test Subflow 2</name>
        <sys_created_by>admin</sys_created_by>
        <sys_created_on>2020-11-21 17:29:29</sys_created_on>
        <sys_id>02beb4bedb2c2010969430d868961915</sys_id>
        <sys_mod_count>0</sys_mod_count>
        <sys_scope/>
        <sys_updated_by>admin</sys_updated_by>
        <sys_updated_on>2020-11-21 17:29:29</sys_updated_on>
    </sys_flow_cat_variable_model>
    <sys_hub_flow_input action="DELETE" query="model=0ebeb4bedb2c2010969430d868961914^sys_idNOT IN1d9485f2db6c2010969430d86896199d,cebeb4bedb2c2010969430d868961915"/>
    <sys_hub_flow_input action="DELETE">
        <active>true</active>
        <array>false</array>
        <array_denormalized>false</array_denormalized>
        <attributes>element_mapping_provider=com.glide.flow_design.action.data.FlowDesignVariableMapper,uiType=reference,uiTypeLabel=Reference,uiUniqueId=8bc7b41a-4665-4dad-8beb-e207993798f2</attributes>
        <audit>false</audit>
        <calculation><![CDATA[(function calculatedFieldValue(current) {

	// Add your code here
	return '';  // return the calculated value

})(current);]]></calculation>
        <choice/>
        <choice_field/>
        <choice_table>x_snc_ethsign_account</choice_table>
        <column_label/>
        <comments/>
        <create_roles/>
        <default_value/>
        <defaultsort/>
        <delete_roles/>
        <dependent/>
        <dependent_on_field/>
        <display>false</display>
        <dynamic_creation>false</dynamic_creation>
        <dynamic_creation_script/>
        <dynamic_default_value/>
        <dynamic_ref_qual/>
        <element>account</element>
        <element_reference>false</element_reference>
        <foreign_database/>
        <function_definition/>
        <function_field>false</function_field>
        <help/>
        <hint/>
        <internal_type display_value="Reference">reference</internal_type>
        <label>account</label>
        <mandatory>true</mandatory>
        <max_length>32</max_length>
        <model display_value="Test Subflow 2">0ebeb4bedb2c2010969430d868961914</model>
        <model_id>0ebeb4bedb2c2010969430d868961914</model_id>
        <model_table>sys_hub_flow_snapshot</model_table>
        <name>var__m_sys_hub_flow_input_0ebeb4bedb2c2010969430d868961914</name>
        <next_element/>
        <order>2</order>
        <primary>false</primary>
        <read_only>false</read_only>
        <read_roles/>
        <reference display_value="" name="x_snc_ethsign_account">x_snc_ethsign_account</reference>
        <reference_cascade_rule/>
        <reference_floats>false</reference_floats>
        <reference_key/>
        <reference_qual/>
        <reference_qual_condition/>
        <reference_type/>
        <sizeclass/>
        <spell_check>false</spell_check>
        <staged>false</staged>
        <sys_class_name>sys_hub_flow_input</sys_class_name>
        <sys_created_by>admin</sys_created_by>
        <sys_created_on>2020-11-21 17:55:06</sys_created_on>
        <sys_id>1d9485f2db6c2010969430d86896199d</sys_id>
        <sys_mod_count>1</sys_mod_count>
        <sys_name/>
        <sys_package/>
        <sys_policy/>
        <sys_scope display_value="Ethereum">3c0e4434db442010969430d868961918</sys_scope>
        <sys_update_name/>
        <sys_updated_by>admin</sys_updated_by>
        <sys_updated_on>2020-11-21 17:55:06</sys_updated_on>
        <table_reference>false</table_reference>
        <text_index>false</text_index>
        <unique>false</unique>
        <use_dependent_field>false</use_dependent_field>
        <use_dynamic_default>false</use_dynamic_default>
        <use_reference_qualifier>simple</use_reference_qualifier>
        <virtual>false</virtual>
        <widget/>
        <write_roles/>
        <xml_view>false</xml_view>
    </sys_hub_flow_input>
    <sys_hub_flow_input action="DELETE">
        <active>true</active>
        <array>false</array>
        <array_denormalized>false</array_denormalized>
        <attributes>element_mapping_provider=com.glide.flow_design.action.data.FlowDesignVariableMapper,uiType=reference,uiTypeLabel=Reference,uiUniqueId=3597a85b-fa8e-468d-a286-e2fcbb81eddf</attributes>
        <audit>false</audit>
        <calculation><![CDATA[(function calculatedFieldValue(current) {

	// Add your code here
	return '';  // return the calculated value

})(current);]]></calculation>
        <choice/>
        <choice_field/>
        <choice_table>x_snc_ethereum_network</choice_table>
        <column_label/>
        <comments/>
        <create_roles/>
        <default_value/>
        <defaultsort/>
        <delete_roles/>
        <dependent/>
        <dependent_on_field/>
        <display>false</display>
        <dynamic_creation>false</dynamic_creation>
        <dynamic_creation_script/>
        <dynamic_default_value/>
        <dynamic_ref_qual/>
        <element>network</element>
        <element_reference>false</element_reference>
        <foreign_database/>
        <function_definition/>
        <function_field>false</function_field>
        <help/>
        <hint/>
        <internal_type display_value="Reference">reference</internal_type>
        <label>network</label>
        <mandatory>true</mandatory>
        <max_length>32</max_length>
        <model display_value="Test Subflow 2">0ebeb4bedb2c2010969430d868961914</model>
        <model_id>0ebeb4bedb2c2010969430d868961914</model_id>
        <model_table>sys_hub_flow_snapshot</model_table>
        <name>var__m_sys_hub_flow_input_0ebeb4bedb2c2010969430d868961914</name>
        <next_element/>
        <order>1</order>
        <primary>false</primary>
        <read_only>false</read_only>
        <read_roles/>
        <reference display_value="" name="x_snc_ethereum_network">x_snc_ethereum_network</reference>
        <reference_cascade_rule/>
        <reference_floats>false</reference_floats>
        <reference_key/>
        <reference_qual/>
        <reference_qual_condition/>
        <reference_type/>
        <sizeclass/>
        <spell_check>false</spell_check>
        <staged>false</staged>
        <sys_class_name>sys_hub_flow_input</sys_class_name>
        <sys_created_by>admin</sys_created_by>
        <sys_created_on>2020-11-21 17:29:29</sys_created_on>
        <sys_id>cebeb4bedb2c2010969430d868961915</sys_id>
        <sys_mod_count>1</sys_mod_count>
        <sys_name/>
        <sys_package/>
        <sys_policy/>
        <sys_scope display_value="Ethereum">3c0e4434db442010969430d868961918</sys_scope>
        <sys_update_name/>
        <sys_updated_by>admin</sys_updated_by>
        <sys_updated_on>2020-11-21 17:29:29</sys_updated_on>
        <table_reference>false</table_reference>
        <text_index>false</text_index>
        <unique>false</unique>
        <use_dependent_field>false</use_dependent_field>
        <use_dynamic_default>false</use_dynamic_default>
        <use_reference_qualifier>simple</use_reference_qualifier>
        <virtual>false</virtual>
        <widget/>
        <write_roles/>
        <xml_view>false</xml_view>
    </sys_hub_flow_input>
    <sys_hub_action_instance action="DELETE" query="flow=0ebeb4bedb2c2010969430d868961914^sys_idNOT IN16beb4bedb2c2010969430d868961932,b9a58536db6c2010969430d86896198c"/>
    <sys_hub_action_instance action="DELETE">
        <action_inputs/>
        <action_inputs/>
        <action_type display_value="Identify Endpoint">1643eb16db602010969430d868961947</action_type>
        <action_type_parent display_value="Identify Endpoint">07b22716db602010969430d868961946</action_type_parent>
        <comment/>
        <compiled_snapshot>1643eb16db602010969430d868961947</compiled_snapshot>
        <display_text/>
        <flow display_value="Test Subflow 2">0ebeb4bedb2c2010969430d868961914</flow>
        <order>1</order>
        <parent_ui_id/>
        <sys_class_name>sys_hub_action_instance</sys_class_name>
        <sys_created_by>admin</sys_created_by>
        <sys_created_on>2020-11-21 17:29:29</sys_created_on>
        <sys_id>16beb4bedb2c2010969430d868961932</sys_id>
        <sys_mod_count>10</sys_mod_count>
        <sys_scope display_value="Ethereum">3c0e4434db442010969430d868961918</sys_scope>
        <sys_updated_by>admin</sys_updated_by>
        <sys_updated_on>2020-11-21 17:59:46</sys_updated_on>
        <ui_id>aece5707-e790-4ab3-87e5-338f0e5b9beb</ui_id>
    </sys_hub_action_instance>
    <sys_variable_value action="DELETE" query="document_key=16beb4bedb2c2010969430d868961932"/>
    <sys_element_mapping action="DELETE" query="id=16beb4bedb2c2010969430d868961932"/>
    <sys_element_mapping action="DELETE">
        <field>network</field>
        <id>16beb4bedb2c2010969430d868961932</id>
        <sys_created_by>admin</sys_created_by>
        <sys_created_on>2020-11-21 17:29:29</sys_created_on>
        <sys_id>52beb4bedb2c2010969430d868961933</sys_id>
        <sys_mod_count>0</sys_mod_count>
        <sys_updated_by>admin</sys_updated_by>
        <sys_updated_on>2020-11-21 17:29:29</sys_updated_on>
        <table>var__m_sys_hub_action_input_1643eb16db602010969430d868961947</table>
        <value>{{subflow.network}}</value>
    </sys_element_mapping>
    <sys_hub_action_instance action="DELETE">
        <action_inputs/>
        <action_inputs/>
        <action_type display_value="Copy of Define Nonce">a8658136db6c2010969430d868961966</action_type>
        <action_type_parent display_value="Copy of Define Nonce">8345cdf2db6c2010969430d8689619d9</action_type_parent>
        <comment/>
        <compiled_snapshot>a8658136db6c2010969430d868961966</compiled_snapshot>
        <display_text/>
        <flow display_value="Test Subflow 2">0ebeb4bedb2c2010969430d868961914</flow>
        <order>2</order>
        <parent_ui_id/>
        <sys_class_name>sys_hub_action_instance</sys_class_name>
        <sys_created_by>admin</sys_created_by>
        <sys_created_on>2020-11-21 17:59:46</sys_created_on>
        <sys_id>b9a58536db6c2010969430d86896198c</sys_id>
        <sys_mod_count>4</sys_mod_count>
        <sys_scope display_value="Ethereum">3c0e4434db442010969430d868961918</sys_scope>
        <sys_updated_by>admin</sys_updated_by>
        <sys_updated_on>2020-11-21 17:59:46</sys_updated_on>
        <ui_id>1356c76a-ba69-4f7b-b5cb-c0fad77117ad</ui_id>
    </sys_hub_action_instance>
    <sys_variable_value action="DELETE" query="document_key=b9a58536db6c2010969430d86896198c"/>
    <sys_element_mapping action="DELETE" query="id=b9a58536db6c2010969430d86896198c"/>
    <sys_element_mapping action="DELETE">
        <field>endpoint</field>
        <id>b9a58536db6c2010969430d86896198c</id>
        <sys_created_by>admin</sys_created_by>
        <sys_created_on>2020-11-21 17:59:46</sys_created_on>
        <sys_id>79a58536db6c2010969430d86896198d</sys_id>
        <sys_mod_count>0</sys_mod_count>
        <sys_updated_by>admin</sys_updated_by>
        <sys_updated_on>2020-11-21 17:59:46</sys_updated_on>
        <table>var__m_sys_hub_action_input_a8658136db6c2010969430d868961966</table>
        <value>{{aece5707-e790-4ab3-87e5-338f0e5b9beb.endpoint}}</value>
    </sys_element_mapping>
    <sys_element_mapping action="DELETE">
        <field>key</field>
        <id>b9a58536db6c2010969430d86896198c</id>
        <sys_created_by>admin</sys_created_by>
        <sys_created_on>2020-11-21 17:59:46</sys_created_on>
        <sys_id>3da58536db6c2010969430d86896198d</sys_id>
        <sys_mod_count>0</sys_mod_count>
        <sys_updated_by>admin</sys_updated_by>
        <sys_updated_on>2020-11-21 17:59:46</sys_updated_on>
        <table>var__m_sys_hub_action_input_a8658136db6c2010969430d868961966</table>
        <value>{{subflow.account.key}}</value>
    </sys_element_mapping>
    <sys_documentation action="DELETE" query="name=var__m_sys_hub_flow_input_0ebeb4bedb2c2010969430d868961914^sys_idNOT IN1ebeb4bedb2c2010969430d86896191c,a19485f2db6c2010969430d8689619a5"/>
    <sys_documentation action="DELETE">
        <element>network</element>
        <help/>
        <hint/>
        <label>network</label>
        <language>en</language>
        <name>var__m_sys_hub_flow_input_0ebeb4bedb2c2010969430d868961914</name>
        <plural/>
        <sys_class_name>sys_documentation</sys_class_name>
        <sys_created_by>admin</sys_created_by>
        <sys_created_on>2020-11-21 17:29:29</sys_created_on>
        <sys_id>1ebeb4bedb2c2010969430d86896191c</sys_id>
        <sys_mod_count>0</sys_mod_count>
        <sys_name/>
        <sys_package display_value="Ethereum" source="x_snc_ethereum">3c0e4434db442010969430d868961918</sys_package>
        <sys_policy/>
        <sys_scope display_value="Ethereum">3c0e4434db442010969430d868961918</sys_scope>
        <sys_update_name/>
        <sys_updated_by>admin</sys_updated_by>
        <sys_updated_on>2020-11-21 17:29:29</sys_updated_on>
        <url/>
        <url_target/>
    </sys_documentation>
    <sys_documentation action="DELETE">
        <element>account</element>
        <help/>
        <hint/>
        <label>account</label>
        <language>en</language>
        <name>var__m_sys_hub_flow_input_0ebeb4bedb2c2010969430d868961914</name>
        <plural/>
        <sys_class_name>sys_documentation</sys_class_name>
        <sys_created_by>admin</sys_created_by>
        <sys_created_on>2020-11-21 17:55:06</sys_created_on>
        <sys_id>a19485f2db6c2010969430d8689619a5</sys_id>
        <sys_mod_count>0</sys_mod_count>
        <sys_name/>
        <sys_package display_value="Ethereum" source="x_snc_ethereum">3c0e4434db442010969430d868961918</sys_package>
        <sys_policy/>
        <sys_scope display_value="Ethereum">3c0e4434db442010969430d868961918</sys_scope>
        <sys_update_name/>
        <sys_updated_by>admin</sys_updated_by>
        <sys_updated_on>2020-11-21 17:55:06</sys_updated_on>
        <url/>
        <url_target/>
    </sys_documentation>
    <sys_update_version action="INSERT_OR_UPDATE">
        <action>DELETE</action>
        <application display_value="Ethereum">3c0e4434db442010969430d868961918</application>
        <file_path/>
        <instance_id>1030efb5db3c9050566750b6f496193d</instance_id>
        <instance_name>ethereum2</instance_name>
        <name>sys_hub_flow_c57db47edb2c2010969430d8689619c7</name>
        <payload>&lt;?xml version="1.0" encoding="UTF-8"?&gt;&lt;record_update sys_domain="global" table="sys_hub_flow"&gt;&lt;sys_hub_flow action="INSERT_OR_UPDATE"&gt;&lt;access&gt;public&lt;/access&gt;&lt;acls/&gt;&lt;active&gt;true&lt;/active&gt;&lt;annotation/&gt;&lt;callable_by_client_api&gt;false&lt;/callable_by_client_api&gt;&lt;category/&gt;&lt;compiler_build/&gt;&lt;copied_from/&gt;&lt;copied_from_name/&gt;&lt;description/&gt;&lt;internal_name&gt;test_subflow_2&lt;/internal_name&gt;&lt;label_cache&gt;[{"name":"1356c76a-ba69-4f7b-b5cb-c0fad77117ad.nonce","label":"2➛nonce","reference_display":"nonce","type":"string","base_type":"string","attributes":{"uiTypeLabel":"String","element_mapping_provider":"com.glide.flow_design.action.data.FlowDesignVariableMapper","pwd2droppable":"true","uiType":"string","uiUniqueId":"3ec58a30-47ed-400d-a21a-b8d88e078456"}},{"name":"subflow.account.key","label":"Input➛account➛Key","reference":"x_snc_ethsign_key","reference_display":"Key","type":"reference","base_type":"reference","parent_table_name":"x_snc_ethsign_account","column_name":"key"},{"name":"aece5707-e790-4ab3-87e5-338f0e5b9beb.endpoint","label":"1➛endpoint","reference":"x_snc_ethereum_endpoint","reference_display":"Endpoint","type":"reference","base_type":"reference","attributes":{"uiType":"reference","uiTypeLabel":"Reference","element_mapping_provider":"com.glide.flow_design.action.data.FlowDesignVariableMapper","uiUniqueId":"61dfb561-5b1a-4f4c-adc0-3f3c6e4f5997"}},{"name":"1f71ceb8-ee44-4e64-9f29-17a2928474ed.nonce","label":"2➛nonce","reference_display":"nonce","type":"string","base_type":"string","attributes":{"uiTypeLabel":"String","element_mapping_provider":"com.glide.flow_design.action.data.FlowDesignVariableMapper","pwd2droppable":"true","uiType":"string","uiUniqueId":"3ec58a30-47ed-400d-a21a-b8d88e078456"}},{"name":"subflow.network","label":"Input➛network","reference":"x_snc_ethereum_network","reference_display":"Network","type":"reference","base_type":"reference","attributes":{"sourceUiUniqueId":"","sourceType":"","sourceId":"","uiUniqueId":"3597a85b-fa8e-468d-a286-e2fcbb81eddf"}}]&lt;/label_cache&gt;&lt;latest_snapshot&gt;0ebeb4bedb2c2010969430d868961914&lt;/latest_snapshot&gt;&lt;master_snapshot&gt;0ebeb4bedb2c2010969430d868961914&lt;/master_snapshot&gt;&lt;name&gt;Test Subflow 2&lt;/name&gt;&lt;natlang/&gt;&lt;outputs/&gt;&lt;remote_trigger_id/&gt;&lt;run_as&gt;user&lt;/run_as&gt;&lt;sc_callable&gt;false&lt;/sc_callable&gt;&lt;show_draft_actions&gt;false&lt;/show_draft_actions&gt;&lt;show_triggered_flows&gt;false&lt;/show_triggered_flows&gt;&lt;status&gt;published&lt;/status&gt;&lt;sys_class_name&gt;sys_hub_flow&lt;/sys_class_name&gt;&lt;sys_created_by&gt;admin&lt;/sys_created_by&gt;&lt;sys_created_on&gt;2020-11-21 17:23:56&lt;/sys_created_on&gt;&lt;sys_domain&gt;global&lt;/sys_domain&gt;&lt;sys_domain_path&gt;/&lt;/sys_domain_path&gt;&lt;sys_id&gt;c57db47edb2c2010969430d8689619c7&lt;/sys_id&gt;&lt;sys_mod_count&gt;10&lt;/sys_mod_count&gt;&lt;sys_name&gt;Test Subflow 2&lt;/sys_name&gt;&lt;sys_overrides/&gt;&lt;sys_package display_value="Ethereum" source="x_snc_ethereum"&gt;3c0e4434db442010969430d868961918&lt;/sys_package&gt;&lt;sys_policy/&gt;&lt;sys_scope display_value="Ethereum"&gt;3c0e4434db442010969430d868961918&lt;/sys_scope&gt;&lt;sys_update_name&gt;sys_hub_flow_c57db47edb2c2010969430d8689619c7&lt;/sys_update_name&gt;&lt;sys_updated_by&gt;admin&lt;/sys_updated_by&gt;&lt;sys_updated_on&gt;2020-11-21 17:59:47&lt;/sys_updated_on&gt;&lt;type&gt;subflow&lt;/type&gt;&lt;/sys_hub_flow&gt;&lt;sys_translated_text action="delete_multiple" query="documentkey=c57db47edb2c2010969430d8689619c7"/&gt;&lt;sys_variable_value action="delete_multiple" query="document_key=c57db47edb2c2010969430d8689619c7"/&gt;&lt;sys_hub_flow_component action="delete_multiple" query="flow=c57db47edb2c2010969430d8689619c7^sys_idNOT IN7f954536db6c2010969430d8689619db,a3ed3c7edb2c2010969430d868961962"/&gt;&lt;sys_hub_action_instance action="INSERT_OR_UPDATE"&gt;&lt;action_inputs/&gt;&lt;action_inputs/&gt;&lt;action_type display_value="Copy of Define Nonce"&gt;a8658136db6c2010969430d868961966&lt;/action_type&gt;&lt;action_type_parent/&gt;&lt;comment/&gt;&lt;compiled_snapshot/&gt;&lt;display_text/&gt;&lt;flow display_value="Test Subflow 2"&gt;c57db47edb2c2010969430d8689619c7&lt;/flow&gt;&lt;order&gt;2&lt;/order&gt;&lt;parent_ui_id/&gt;&lt;sys_class_name&gt;sys_hub_action_instance&lt;/sys_class_name&gt;&lt;sys_created_by&gt;admin&lt;/sys_created_by&gt;&lt;sys_created_on&gt;2020-11-21 17:59:38&lt;/sys_created_on&gt;&lt;sys_id&gt;7f954536db6c2010969430d8689619db&lt;/sys_id&gt;&lt;sys_mod_count&gt;6&lt;/sys_mod_count&gt;&lt;sys_scope display_value="Ethereum"&gt;3c0e4434db442010969430d868961918&lt;/sys_scope&gt;&lt;sys_updated_by&gt;admin&lt;/sys_updated_by&gt;&lt;sys_updated_on&gt;2020-11-21 17:59:47&lt;/sys_updated_on&gt;&lt;ui_id&gt;1356c76a-ba69-4f7b-b5cb-c0fad77117ad&lt;/ui_id&gt;&lt;/sys_hub_action_instance&gt;&lt;sys_variable_value action="delete_multiple" query="document_key=7f954536db6c2010969430d8689619db"/&gt;&lt;sys_element_mapping action="delete_multiple" query="id=7f954536db6c2010969430d8689619db"/&gt;&lt;sys_element_mapping action="INSERT_OR_UPDATE"&gt;&lt;field&gt;endpoint&lt;/field&gt;&lt;id&gt;7f954536db6c2010969430d8689619db&lt;/id&gt;&lt;sys_created_by&gt;admin&lt;/sys_created_by&gt;&lt;sys_created_on&gt;2020-11-21 17:59:38&lt;/sys_created_on&gt;&lt;sys_id&gt;f7954536db6c2010969430d8689619dd&lt;/sys_id&gt;&lt;sys_mod_count&gt;0&lt;/sys_mod_count&gt;&lt;sys_updated_by&gt;admin&lt;/sys_updated_by&gt;&lt;sys_updated_on&gt;2020-11-21 17:59:38&lt;/sys_updated_on&gt;&lt;table&gt;var__m_sys_hub_action_input_a8658136db6c2010969430d868961966&lt;/table&gt;&lt;value&gt;{{aece5707-e790-4ab3-87e5-338f0e5b9beb.endpoint}}&lt;/value&gt;&lt;/sys_element_mapping&gt;&lt;sys_element_mapping action="INSERT_OR_UPDATE"&gt;&lt;field&gt;key&lt;/field&gt;&lt;id&gt;7f954536db6c2010969430d8689619db&lt;/id&gt;&lt;sys_created_by&gt;admin&lt;/sys_created_by&gt;&lt;sys_created_on&gt;2020-11-21 17:59:38&lt;/sys_created_on&gt;&lt;sys_id&gt;bb954536db6c2010969430d8689619dd&lt;/sys_id&gt;&lt;sys_mod_count&gt;0&lt;/sys_mod_count&gt;&lt;sys_updated_by&gt;admin&lt;/sys_updated_by&gt;&lt;sys_updated_on&gt;2020-11-21 17:59:38&lt;/sys_updated_on&gt;&lt;table&gt;var__m_sys_hub_action_input_a8658136db6c2010969430d868961966&lt;/table&gt;&lt;value&gt;{{subflow.account.key}}&lt;/value&gt;&lt;/sys_element_mapping&gt;&lt;sys_hub_action_instance action="INSERT_OR_UPDATE"&gt;&lt;action_inputs/&gt;&lt;action_inputs/&gt;&lt;action_type display_value="Identify Endpoint"&gt;1643eb16db602010969430d868961947&lt;/action_type&gt;&lt;action_type_parent/&gt;&lt;comment/&gt;&lt;compiled_snapshot/&gt;&lt;display_text/&gt;&lt;flow display_value="Test Subflow 2"&gt;c57db47edb2c2010969430d8689619c7&lt;/flow&gt;&lt;order&gt;1&lt;/order&gt;&lt;parent_ui_id/&gt;&lt;sys_class_name&gt;sys_hub_action_instance&lt;/sys_class_name&gt;&lt;sys_created_by&gt;admin&lt;/sys_created_by&gt;&lt;sys_created_on&gt;2020-11-21 17:26:02&lt;/sys_created_on&gt;&lt;sys_id&gt;a3ed3c7edb2c2010969430d868961962&lt;/sys_id&gt;&lt;sys_mod_count&gt;20&lt;/sys_mod_count&gt;&lt;sys_scope display_value="Ethereum"&gt;3c0e4434db442010969430d868961918&lt;/sys_scope&gt;&lt;sys_updated_by&gt;admin&lt;/sys_updated_by&gt;&lt;sys_updated_on&gt;2020-11-21 17:59:47&lt;/sys_updated_on&gt;&lt;ui_id&gt;aece5707-e790-4ab3-87e5-338f0e5b9beb&lt;/ui_id&gt;&lt;/sys_hub_action_instance&gt;&lt;sys_variable_value action="delete_multiple" query="document_key=a3ed3c7edb2c2010969430d868961962"/&gt;&lt;sys_element_mapping action="delete_multiple" query="id=a3ed3c7edb2c2010969430d868961962"/&gt;&lt;sys_element_mapping action="INSERT_OR_UPDATE"&gt;&lt;field&gt;network&lt;/field&gt;&lt;id&gt;a3ed3c7edb2c2010969430d868961962&lt;/id&gt;&lt;sys_created_by&gt;admin&lt;/sys_created_by&gt;&lt;sys_created_on&gt;2020-11-21 17:26:02&lt;/sys_created_on&gt;&lt;sys_id&gt;6fed3c7edb2c2010969430d868961963&lt;/sys_id&gt;&lt;sys_mod_count&gt;0&lt;/sys_mod_count&gt;&lt;sys_updated_by&gt;admin&lt;/sys_updated_by&gt;&lt;sys_updated_on&gt;2020-11-21 17:26:02&lt;/sys_updated_on&gt;&lt;table&gt;var__m_sys_hub_action_input_1643eb16db602010969430d868961947&lt;/table&gt;&lt;value&gt;{{subflow.network}}&lt;/value&gt;&lt;/sys_element_mapping&gt;&lt;sys_flow_cat_variable_model action="delete_multiple" query="id=c57db47edb2c2010969430d8689619c7^sys_idNOT IN8d7db47edb2c2010969430d8689619c9"/&gt;&lt;sys_flow_cat_variable_model action="INSERT_OR_UPDATE"&gt;&lt;id&gt;c57db47edb2c2010969430d8689619c7&lt;/id&gt;&lt;name&gt;Test Subflow 2&lt;/name&gt;&lt;sys_created_by&gt;admin&lt;/sys_created_by&gt;&lt;sys_created_on&gt;2020-11-21 17:23:56&lt;/sys_created_on&gt;&lt;sys_id&gt;8d7db47edb2c2010969430d8689619c9&lt;/sys_id&gt;&lt;sys_mod_count&gt;0&lt;/sys_mod_count&gt;&lt;sys_scope/&gt;&lt;sys_updated_by&gt;admin&lt;/sys_updated_by&gt;&lt;sys_updated_on&gt;2020-11-21 17:23:56&lt;/sys_updated_on&gt;&lt;/sys_flow_cat_variable_model&gt;&lt;sys_hub_flow_input action="delete_multiple" query="model=c57db47edb2c2010969430d8689619c7^sys_idNOT IN0f92c172db6c2010969430d868961918,67edb87edb2c2010969430d868961948"/&gt;&lt;sys_hub_flow_input action="INSERT_OR_UPDATE"&gt;&lt;active&gt;true&lt;/active&gt;&lt;array&gt;false&lt;/array&gt;&lt;array_denormalized&gt;false&lt;/array_denormalized&gt;&lt;attributes&gt;element_mapping_provider=com.glide.flow_design.action.data.FlowDesignVariableMapper,uiType=reference,uiTypeLabel=Reference,uiUniqueId=8bc7b41a-4665-4dad-8beb-e207993798f2&lt;/attributes&gt;&lt;audit&gt;false&lt;/audit&gt;&lt;calculation&gt;&lt;![CDATA[(function calculatedFieldValue(current) {

	// Add your code here
	return '';  // return the calculated value

})(current);]]&gt;&lt;/calculation&gt;&lt;choice/&gt;&lt;choice_field/&gt;&lt;choice_table&gt;x_snc_ethsign_account&lt;/choice_table&gt;&lt;column_label/&gt;&lt;comments/&gt;&lt;create_roles/&gt;&lt;default_value/&gt;&lt;defaultsort/&gt;&lt;delete_roles/&gt;&lt;dependent/&gt;&lt;dependent_on_field/&gt;&lt;display&gt;false&lt;/display&gt;&lt;dynamic_creation&gt;false&lt;/dynamic_creation&gt;&lt;dynamic_creation_script/&gt;&lt;dynamic_default_value/&gt;&lt;dynamic_ref_qual/&gt;&lt;element&gt;account&lt;/element&gt;&lt;element_reference&gt;false&lt;/element_reference&gt;&lt;foreign_database/&gt;&lt;function_definition/&gt;&lt;function_field&gt;false&lt;/function_field&gt;&lt;help/&gt;&lt;hint/&gt;&lt;internal_type display_value="Reference"&gt;reference&lt;/internal_type&gt;&lt;label&gt;account&lt;/label&gt;&lt;mandatory&gt;true&lt;/mandatory&gt;&lt;max_length&gt;32&lt;/max_length&gt;&lt;model display_value="Test Subflow 2"&gt;c57db47edb2c2010969430d8689619c7&lt;/model&gt;&lt;model_id&gt;c57db47edb2c2010969430d8689619c7&lt;/model_id&gt;&lt;model_table&gt;sys_hub_flow&lt;/model_table&gt;&lt;name&gt;var__m_sys_hub_flow_input_c57db47edb2c2010969430d8689619c7&lt;/name&gt;&lt;next_element/&gt;&lt;order&gt;2&lt;/order&gt;&lt;primary&gt;false&lt;/primary&gt;&lt;read_only&gt;false&lt;/read_only&gt;&lt;read_roles/&gt;&lt;reference display_value="" name="x_snc_ethsign_account"&gt;x_snc_ethsign_account&lt;/reference&gt;&lt;reference_cascade_rule/&gt;&lt;reference_floats&gt;false&lt;/reference_floats&gt;&lt;reference_key/&gt;&lt;reference_qual/&gt;&lt;reference_qual_condition/&gt;&lt;reference_type/&gt;&lt;sizeclass/&gt;&lt;spell_check&gt;false&lt;/spell_check&gt;&lt;staged&gt;false&lt;/staged&gt;&lt;sys_class_name&gt;sys_hub_flow_input&lt;/sys_class_name&gt;&lt;sys_created_by&gt;admin&lt;/sys_created_by&gt;&lt;sys_created_on&gt;2020-11-21 17:46:28&lt;/sys_created_on&gt;&lt;sys_id&gt;0f92c172db6c2010969430d868961918&lt;/sys_id&gt;&lt;sys_mod_count&gt;1&lt;/sys_mod_count&gt;&lt;sys_name/&gt;&lt;sys_package/&gt;&lt;sys_policy/&gt;&lt;sys_scope display_value="Ethereum"&gt;3c0e4434db442010969430d868961918&lt;/sys_scope&gt;&lt;sys_update_name/&gt;&lt;sys_updated_by&gt;admin&lt;/sys_updated_by&gt;&lt;sys_updated_on&gt;2020-11-21 17:46:28&lt;/sys_updated_on&gt;&lt;table_reference&gt;false&lt;/table_reference&gt;&lt;text_index&gt;false&lt;/text_index&gt;&lt;unique&gt;false&lt;/unique&gt;&lt;use_dependent_field&gt;false&lt;/use_dependent_field&gt;&lt;use_dynamic_default&gt;false&lt;/use_dynamic_default&gt;&lt;use_reference_qualifier&gt;simple&lt;/use_reference_qualifier&gt;&lt;virtual&gt;false&lt;/virtual&gt;&lt;widget/&gt;&lt;write_roles/&gt;&lt;xml_view&gt;false&lt;/xml_view&gt;&lt;/sys_hub_flow_input&gt;&lt;sys_hub_flow_input action="INSERT_OR_UPDATE"&gt;&lt;active&gt;true&lt;/active&gt;&lt;array&gt;false&lt;/array&gt;&lt;array_denormalized&gt;false&lt;/array_denormalized&gt;&lt;attributes&gt;element_mapping_provider=com.glide.flow_design.action.data.FlowDesignVariableMapper,uiType=reference,uiTypeLabel=Reference,uiUniqueId=3597a85b-fa8e-468d-a286-e2fcbb81eddf&lt;/attributes&gt;&lt;audit&gt;false&lt;/audit&gt;&lt;calculation&gt;&lt;![CDATA[(function calculatedFieldValue(current) {

	// Add your code here
	return '';  // return the calculated value

})(current);]]&gt;&lt;/calculation&gt;&lt;choice/&gt;&lt;choice_field/&gt;&lt;choice_table&gt;x_snc_ethereum_network&lt;/choice_table&gt;&lt;column_label/&gt;&lt;comments/&gt;&lt;create_roles/&gt;&lt;default_value/&gt;&lt;defaultsort/&gt;&lt;delete_roles/&gt;&lt;dependent/&gt;&lt;dependent_on_field/&gt;&lt;display&gt;false&lt;/display&gt;&lt;dynamic_creation&gt;false&lt;/dynamic_creation&gt;&lt;dynamic_creation_script/&gt;&lt;dynamic_default_value/&gt;&lt;dynamic_ref_qual/&gt;&lt;element&gt;network&lt;/element&gt;&lt;element_reference&gt;false&lt;/element_reference&gt;&lt;foreign_database/&gt;&lt;function_definition/&gt;&lt;function_field&gt;false&lt;/function_field&gt;&lt;help/&gt;&lt;hint/&gt;&lt;internal_type display_value="Reference"&gt;reference&lt;/internal_type&gt;&lt;label&gt;network&lt;/label&gt;&lt;mandatory&gt;true&lt;/mandatory&gt;&lt;max_length&gt;32&lt;/max_length&gt;&lt;model display_value="Test Subflow 2"&gt;c57db47edb2c2010969430d8689619c7&lt;/model&gt;&lt;model_id&gt;c57db47edb2c2010969430d8689619c7&lt;/model_id&gt;&lt;model_table&gt;sys_hub_flow&lt;/model_table&gt;&lt;name&gt;var__m_sys_hub_flow_input_c57db47edb2c2010969430d8689619c7&lt;/name&gt;&lt;next_element/&gt;&lt;order&gt;1&lt;/order&gt;&lt;primary&gt;false&lt;/primary&gt;&lt;read_only&gt;false&lt;/read_only&gt;&lt;read_roles/&gt;&lt;reference display_value="" name="x_snc_ethereum_network"&gt;x_snc_ethereum_network&lt;/reference&gt;&lt;reference_cascade_rule/&gt;&lt;reference_floats&gt;false&lt;/reference_floats&gt;&lt;reference_key/&gt;&lt;reference_qual/&gt;&lt;reference_qual_condition/&gt;&lt;reference_type/&gt;&lt;sizeclass/&gt;&lt;spell_check&gt;false&lt;/spell_check&gt;&lt;staged&gt;false&lt;/staged&gt;&lt;sys_class_name&gt;sys_hub_flow_input&lt;/sys_class_name&gt;&lt;sys_created_by&gt;admin&lt;/sys_created_by&gt;&lt;sys_created_on&gt;2020-11-21 17:26:01&lt;/sys_created_on&gt;&lt;sys_id&gt;67edb87edb2c2010969430d868961948&lt;/sys_id&gt;&lt;sys_mod_count&gt;1&lt;/sys_mod_count&gt;&lt;sys_name/&gt;&lt;sys_package/&gt;&lt;sys_policy/&gt;&lt;sys_scope display_value="Ethereum"&gt;3c0e4434db442010969430d868961918&lt;/sys_scope&gt;&lt;sys_update_name/&gt;&lt;sys_updated_by&gt;admin&lt;/sys_updated_by&gt;&lt;sys_updated_on&gt;2020-11-21 17:26:02&lt;/sys_updated_on&gt;&lt;table_reference&gt;false&lt;/table_reference&gt;&lt;text_index&gt;false&lt;/text_index&gt;&lt;unique&gt;false&lt;/unique&gt;&lt;use_dependent_field&gt;false&lt;/use_dependent_field&gt;&lt;use_dynamic_default&gt;false&lt;/use_dynamic_default&gt;&lt;use_reference_qualifier&gt;simple&lt;/use_reference_qualifier&gt;&lt;virtual&gt;false&lt;/virtual&gt;&lt;widget/&gt;&lt;write_roles/&gt;&lt;xml_view&gt;false&lt;/xml_view&gt;&lt;/sys_hub_flow_input&gt;&lt;sys_hub_action_instance action="delete_multiple" query="flow=c57db47edb2c2010969430d8689619c7^sys_idNOT IN7f954536db6c2010969430d8689619db,a3ed3c7edb2c2010969430d868961962"/&gt;&lt;sys_hub_action_instance action="INSERT_OR_UPDATE"&gt;&lt;action_inputs/&gt;&lt;action_inputs/&gt;&lt;action_type display_value="Copy of Define Nonce"&gt;a8658136db6c2010969430d868961966&lt;/action_type&gt;&lt;action_type_parent/&gt;&lt;comment/&gt;&lt;compiled_snapshot/&gt;&lt;display_text/&gt;&lt;flow display_value="Test Subflow 2"&gt;c57db47edb2c2010969430d8689619c7&lt;/flow&gt;&lt;order&gt;2&lt;/order&gt;&lt;parent_ui_id/&gt;&lt;sys_class_name&gt;sys_hub_action_instance&lt;/sys_class_name&gt;&lt;sys_created_by&gt;admin&lt;/sys_created_by&gt;&lt;sys_created_on&gt;2020-11-21 17:59:38&lt;/sys_created_on&gt;&lt;sys_id&gt;7f954536db6c2010969430d8689619db&lt;/sys_id&gt;&lt;sys_mod_count&gt;6&lt;/sys_mod_count&gt;&lt;sys_scope display_value="Ethereum"&gt;3c0e4434db442010969430d868961918&lt;/sys_scope&gt;&lt;sys_updated_by&gt;admin&lt;/sys_updated_by&gt;&lt;sys_updated_on&gt;2020-11-21 17:59:47&lt;/sys_updated_on&gt;&lt;ui_id&gt;1356c76a-ba69-4f7b-b5cb-c0fad77117ad&lt;/ui_id&gt;&lt;/sys_hub_action_instance&gt;&lt;sys_variable_value action="delete_multiple" query="document_key=7f954536db6c2010969430d8689619db"/&gt;&lt;sys_element_mapping action="delete_multiple" query="id=7f954536db6c2010969430d8689619db"/&gt;&lt;sys_element_mapping action="INSERT_OR_UPDATE"&gt;&lt;field&gt;endpoint&lt;/field&gt;&lt;id&gt;7f954536db6c2010969430d8689619db&lt;/id&gt;&lt;sys_created_by&gt;admin&lt;/sys_created_by&gt;&lt;sys_created_on&gt;2020-11-21 17:59:38&lt;/sys_created_on&gt;&lt;sys_id&gt;f7954536db6c2010969430d8689619dd&lt;/sys_id&gt;&lt;sys_mod_count&gt;0&lt;/sys_mod_count&gt;&lt;sys_updated_by&gt;admin&lt;/sys_updated_by&gt;&lt;sys_updated_on&gt;2020-11-21 17:59:38&lt;/sys_updated_on&gt;&lt;table&gt;var__m_sys_hub_action_input_a8658136db6c2010969430d868961966&lt;/table&gt;&lt;value&gt;{{aece5707-e790-4ab3-87e5-338f0e5b9beb.endpoint}}&lt;/value&gt;&lt;/sys_element_mapping&gt;&lt;sys_element_mapping action="INSERT_OR_UPDATE"&gt;&lt;field&gt;key&lt;/field&gt;&lt;id&gt;7f954536db6c2010969430d8689619db&lt;/id&gt;&lt;sys_created_by&gt;admin&lt;/sys_created_by&gt;&lt;sys_created_on&gt;2020-11-21 17:59:38&lt;/sys_created_on&gt;&lt;sys_id&gt;bb954536db6c2010969430d8689619dd&lt;/sys_id&gt;&lt;sys_mod_count&gt;0&lt;/sys_mod_count&gt;&lt;sys_updated_by&gt;admin&lt;/sys_updated_by&gt;&lt;sys_updated_on&gt;2020-11-21 17:59:38&lt;/sys_updated_on&gt;&lt;table&gt;var__m_sys_hub_action_input_a8658136db6c2010969430d868961966&lt;/table&gt;&lt;value&gt;{{subflow.account.key}}&lt;/value&gt;&lt;/sys_element_mapping&gt;&lt;sys_hub_action_instance action="INSERT_OR_UPDATE"&gt;&lt;action_inputs/&gt;&lt;action_inputs/&gt;&lt;action_type display_value="Identify Endpoint"&gt;1643eb16db602010969430d868961947&lt;/action_type&gt;&lt;action_type_parent/&gt;&lt;comment/&gt;&lt;compiled_snapshot/&gt;&lt;display_text/&gt;&lt;flow display_value="Test Subflow 2"&gt;c57db47edb2c2010969430d8689619c7&lt;/flow&gt;&lt;order&gt;1&lt;/order&gt;&lt;parent_ui_id/&gt;&lt;sys_class_name&gt;sys_hub_action_instance&lt;/sys_class_name&gt;&lt;sys_created_by&gt;admin&lt;/sys_created_by&gt;&lt;sys_created_on&gt;2020-11-21 17:26:02&lt;/sys_created_on&gt;&lt;sys_id&gt;a3ed3c7edb2c2010969430d868961962&lt;/sys_id&gt;&lt;sys_mod_count&gt;20&lt;/sys_mod_count&gt;&lt;sys_scope display_value="Ethereum"&gt;3c0e4434db442010969430d868961918&lt;/sys_scope&gt;&lt;sys_updated_by&gt;admin&lt;/sys_updated_by&gt;&lt;sys_updated_on&gt;2020-11-21 17:59:47&lt;/sys_updated_on&gt;&lt;ui_id&gt;aece5707-e790-4ab3-87e5-338f0e5b9beb&lt;/ui_id&gt;&lt;/sys_hub_action_instance&gt;&lt;sys_variable_value action="delete_multiple" query="document_key=a3ed3c7edb2c2010969430d868961962"/&gt;&lt;sys_element_mapping action="delete_multiple" query="id=a3ed3c7edb2c2010969430d868961962"/&gt;&lt;sys_element_mapping action="INSERT_OR_UPDATE"&gt;&lt;field&gt;network&lt;/field&gt;&lt;id&gt;a3ed3c7edb2c2010969430d868961962&lt;/id&gt;&lt;sys_created_by&gt;admin&lt;/sys_created_by&gt;&lt;sys_created_on&gt;2020-11-21 17:26:02&lt;/sys_created_on&gt;&lt;sys_id&gt;6fed3c7edb2c2010969430d868961963&lt;/sys_id&gt;&lt;sys_mod_count&gt;0&lt;/sys_mod_count&gt;&lt;sys_updated_by&gt;admin&lt;/sys_updated_by&gt;&lt;sys_updated_on&gt;2020-11-21 17:26:02&lt;/sys_updated_on&gt;&lt;table&gt;var__m_sys_hub_action_input_1643eb16db602010969430d868961947&lt;/table&gt;&lt;value&gt;{{subflow.network}}&lt;/value&gt;&lt;/sys_element_mapping&gt;&lt;sys_documentation action="delete_multiple" query="name=var__m_sys_hub_flow_input_c57db47edb2c2010969430d8689619c7^sys_idNOT IN8f92c172db6c2010969430d86896191e,e7ed3c7edb2c2010969430d86896195c"/&gt;&lt;sys_documentation action="INSERT_OR_UPDATE"&gt;&lt;element&gt;account&lt;/element&gt;&lt;help/&gt;&lt;hint/&gt;&lt;label&gt;account&lt;/label&gt;&lt;language&gt;en&lt;/language&gt;&lt;name&gt;var__m_sys_hub_flow_input_c57db47edb2c2010969430d8689619c7&lt;/name&gt;&lt;plural/&gt;&lt;sys_class_name&gt;sys_documentation&lt;/sys_class_name&gt;&lt;sys_created_by&gt;admin&lt;/sys_created_by&gt;&lt;sys_created_on&gt;2020-11-21 17:46:28&lt;/sys_created_on&gt;&lt;sys_id&gt;8f92c172db6c2010969430d86896191e&lt;/sys_id&gt;&lt;sys_mod_count&gt;0&lt;/sys_mod_count&gt;&lt;sys_name/&gt;&lt;sys_package display_value="Ethereum" source="x_snc_ethereum"&gt;3c0e4434db442010969430d868961918&lt;/sys_package&gt;&lt;sys_policy/&gt;&lt;sys_scope display_value="Ethereum"&gt;3c0e4434db442010969430d868961918&lt;/sys_scope&gt;&lt;sys_update_name/&gt;&lt;sys_updated_by&gt;admin&lt;/sys_updated_by&gt;&lt;sys_updated_on&gt;2020-11-21 17:46:28&lt;/sys_updated_on&gt;&lt;url/&gt;&lt;url_target/&gt;&lt;/sys_documentation&gt;&lt;sys_documentation action="INSERT_OR_UPDATE"&gt;&lt;element&gt;network&lt;/element&gt;&lt;help/&gt;&lt;hint/&gt;&lt;label&gt;network&lt;/label&gt;&lt;language&gt;en&lt;/language&gt;&lt;name&gt;var__m_sys_hub_flow_input_c57db47edb2c2010969430d8689619c7&lt;/name&gt;&lt;plural/&gt;&lt;sys_class_name&gt;sys_documentation&lt;/sys_class_name&gt;&lt;sys_created_by&gt;admin&lt;/sys_created_by&gt;&lt;sys_created_on&gt;2020-11-21 17:26:02&lt;/sys_created_on&gt;&lt;sys_id&gt;e7ed3c7edb2c2010969430d86896195c&lt;/sys_id&gt;&lt;sys_mod_count&gt;0&lt;/sys_mod_count&gt;&lt;sys_name/&gt;&lt;sys_package display_value="Ethereum" source="x_snc_ethereum"&gt;3c0e4434db442010969430d868961918&lt;/sys_package&gt;&lt;sys_policy/&gt;&lt;sys_scope display_value="Ethereum"&gt;3c0e4434db442010969430d868961918&lt;/sys_scope&gt;&lt;sys_update_name/&gt;&lt;sys_updated_by&gt;admin&lt;/sys_updated_by&gt;&lt;sys_updated_on&gt;2020-11-21 17:26:02&lt;/sys_updated_on&gt;&lt;url/&gt;&lt;url_target/&gt;&lt;/sys_documentation&gt;&lt;sys_flow_subflow_plan action="delete_multiple" query="plan_id=c57db47edb2c2010969430d8689619c7^sys_idNOT INe2beb4bedb2c2010969430d868961976"/&gt;&lt;sys_flow_subflow_plan action="INSERT_OR_UPDATE"&gt;&lt;plan&gt;com.snc.process_flow.engine.ProcessPlan@59f07a&lt;/plan&gt;&lt;plan_id display_value="Test Subflow 2"&gt;c57db47edb2c2010969430d8689619c7&lt;/plan_id&gt;&lt;snapshot&gt;0ebeb4bedb2c2010969430d868961914&lt;/snapshot&gt;&lt;sys_created_by&gt;admin&lt;/sys_created_by&gt;&lt;sys_created_on&gt;2020-11-21 17:29:30&lt;/sys_created_on&gt;&lt;sys_domain&gt;global&lt;/sys_domain&gt;&lt;sys_domain_path&gt;/&lt;/sys_domain_path&gt;&lt;sys_id&gt;e2beb4bedb2c2010969430d868961976&lt;/sys_id&gt;&lt;sys_mod_count&gt;2&lt;/sys_mod_count&gt;&lt;sys_overrides/&gt;&lt;sys_scope/&gt;&lt;sys_updated_by&gt;admin&lt;/sys_updated_by&gt;&lt;sys_updated_on&gt;2020-11-21 17:59:47&lt;/sys_updated_on&gt;&lt;/sys_flow_subflow_plan&gt;&lt;sys_hub_flow_snapshot action="INSERT_OR_UPDATE"&gt;&lt;access&gt;public&lt;/access&gt;&lt;acls/&gt;&lt;active&gt;true&lt;/active&gt;&lt;annotation/&gt;&lt;callable_by_client_api&gt;false&lt;/callable_by_client_api&gt;&lt;category/&gt;&lt;copied_from/&gt;&lt;copied_from_name/&gt;&lt;description/&gt;&lt;internal_name&gt;test_subflow_2&lt;/internal_name&gt;&lt;label_cache&gt;[{"name":"1356c76a-ba69-4f7b-b5cb-c0fad77117ad.nonce","label":"2➛nonce","reference_display":"nonce","type":"string","base_type":"string","attributes":{"uiTypeLabel":"String","element_mapping_provider":"com.glide.flow_design.action.data.FlowDesignVariableMapper","pwd2droppable":"true","uiType":"string","uiUniqueId":"3ec58a30-47ed-400d-a21a-b8d88e078456"}},{"name":"subflow.account.key","label":"Input➛account➛Key","reference":"x_snc_ethsign_key","reference_display":"Key","type":"reference","base_type":"reference","parent_table_name":"x_snc_ethsign_account","column_name":"key"},{"name":"aece5707-e790-4ab3-87e5-338f0e5b9beb.endpoint","label":"1➛endpoint","reference":"x_snc_ethereum_endpoint","reference_display":"Endpoint","type":"reference","base_type":"reference","attributes":{"uiType":"reference","uiTypeLabel":"Reference","element_mapping_provider":"com.glide.flow_design.action.data.FlowDesignVariableMapper","uiUniqueId":"61dfb561-5b1a-4f4c-adc0-3f3c6e4f5997"}},{"name":"1f71ceb8-ee44-4e64-9f29-17a2928474ed.nonce","label":"2➛nonce","reference_display":"nonce","type":"string","base_type":"string","attributes":{"uiTypeLabel":"String","element_mapping_provider":"com.glide.flow_design.action.data.FlowDesignVariableMapper","pwd2droppable":"true","uiType":"string","uiUniqueId":"3ec58a30-47ed-400d-a21a-b8d88e078456"}},{"name":"subflow.network","label":"Input➛network","reference":"x_snc_ethereum_network","reference_display":"Network","type":"reference","base_type":"reference","attributes":{"sourceUiUniqueId":"","sourceType":"","sourceId":"","uiUniqueId":"3597a85b-fa8e-468d-a286-e2fcbb81eddf"}}]&lt;/label_cache&gt;&lt;master&gt;true&lt;/master&gt;&lt;name&gt;Test Subflow 2&lt;/name&gt;&lt;natlang/&gt;&lt;outputs/&gt;&lt;parent_flow display_value="Test Subflow 2"&gt;c57db47edb2c2010969430d8689619c7&lt;/parent_flow&gt;&lt;remote_trigger_id/&gt;&lt;run_as&gt;user&lt;/run_as&gt;&lt;sc_callable&gt;false&lt;/sc_callable&gt;&lt;status&gt;published&lt;/status&gt;&lt;sys_class_name&gt;sys_hub_flow_snapshot&lt;/sys_class_name&gt;&lt;sys_created_by&gt;admin&lt;/sys_created_by&gt;&lt;sys_created_on&gt;2020-11-21 17:29:29&lt;/sys_created_on&gt;&lt;sys_domain&gt;global&lt;/sys_domain&gt;&lt;sys_domain_path&gt;/&lt;/sys_domain_path&gt;&lt;sys_id&gt;0ebeb4bedb2c2010969430d868961914&lt;/sys_id&gt;&lt;sys_mod_count&gt;2&lt;/sys_mod_count&gt;&lt;sys_name/&gt;&lt;sys_overrides/&gt;&lt;sys_package/&gt;&lt;sys_policy/&gt;&lt;sys_scope display_value="Ethereum"&gt;3c0e4434db442010969430d868961918&lt;/sys_scope&gt;&lt;sys_update_name/&gt;&lt;sys_updated_by&gt;admin&lt;/sys_updated_by&gt;&lt;sys_updated_on&gt;2020-11-21 17:59:46&lt;/sys_updated_on&gt;&lt;type&gt;subflow&lt;/type&gt;&lt;/sys_hub_flow_snapshot&gt;&lt;sys_translated_text action="delete_multiple" query="documentkey=0ebeb4bedb2c2010969430d868961914"/&gt;&lt;sys_variable_value action="delete_multiple" query="document_key=0ebeb4bedb2c2010969430d868961914"/&gt;&lt;sys_hub_flow_component action="delete_multiple" query="flow=0ebeb4bedb2c2010969430d868961914^sys_idNOT IN16beb4bedb2c2010969430d868961932,b9a58536db6c2010969430d86896198c"/&gt;&lt;sys_hub_action_instance action="INSERT_OR_UPDATE"&gt;&lt;action_inputs/&gt;&lt;action_inputs/&gt;&lt;action_type display_value="Identify Endpoint"&gt;1643eb16db602010969430d868961947&lt;/action_type&gt;&lt;action_type_parent display_value="Identify Endpoint"&gt;07b22716db602010969430d868961946&lt;/action_type_parent&gt;&lt;comment/&gt;&lt;compiled_snapshot&gt;1643eb16db602010969430d868961947&lt;/compiled_snapshot&gt;&lt;display_text/&gt;&lt;flow display_value="Test Subflow 2"&gt;0ebeb4bedb2c2010969430d868961914&lt;/flow&gt;&lt;order&gt;1&lt;/order&gt;&lt;parent_ui_id/&gt;&lt;sys_class_name&gt;sys_hub_action_instance&lt;/sys_class_name&gt;&lt;sys_created_by&gt;admin&lt;/sys_created_by&gt;&lt;sys_created_on&gt;2020-11-21 17:29:29&lt;/sys_created_on&gt;&lt;sys_id&gt;16beb4bedb2c2010969430d868961932&lt;/sys_id&gt;&lt;sys_mod_count&gt;10&lt;/sys_mod_count&gt;&lt;sys_scope display_value="Ethereum"&gt;3c0e4434db442010969430d868961918&lt;/sys_scope&gt;&lt;sys_updated_by&gt;admin&lt;/sys_updated_by&gt;&lt;sys_updated_on&gt;2020-11-21 17:59:46&lt;/sys_updated_on&gt;&lt;ui_id&gt;aece5707-e790-4ab3-87e5-338f0e5b9beb&lt;/ui_id&gt;&lt;/sys_hub_action_instance&gt;&lt;sys_variable_value action="delete_multiple" query="document_key=16beb4bedb2c2010969430d868961932"/&gt;&lt;sys_element_mapping action="delete_multiple" query="id=16beb4bedb2c2010969430d868961932"/&gt;&lt;sys_element_mapping action="INSERT_OR_UPDATE"&gt;&lt;field&gt;network&lt;/field&gt;&lt;id&gt;16beb4bedb2c2010969430d868961932&lt;/id&gt;&lt;sys_created_by&gt;admin&lt;/sys_created_by&gt;&lt;sys_created_on&gt;2020-11-21 17:29:29&lt;/sys_created_on&gt;&lt;sys_id&gt;52beb4bedb2c2010969430d868961933&lt;/sys_id&gt;&lt;sys_mod_count&gt;0&lt;/sys_mod_count&gt;&lt;sys_updated_by&gt;admin&lt;/sys_updated_by&gt;&lt;sys_updated_on&gt;2020-11-21 17:29:29&lt;/sys_updated_on&gt;&lt;table&gt;var__m_sys_hub_action_input_1643eb16db602010969430d868961947&lt;/table&gt;&lt;value&gt;{{subflow.network}}&lt;/value&gt;&lt;/sys_element_mapping&gt;&lt;sys_hub_action_instance action="INSERT_OR_UPDATE"&gt;&lt;action_inputs/&gt;&lt;action_inputs/&gt;&lt;action_type display_value="Copy of Define Nonce"&gt;a8658136db6c2010969430d868961966&lt;/action_type&gt;&lt;action_type_parent display_value="Copy of Define Nonce"&gt;8345cdf2db6c2010969430d8689619d9&lt;/action_type_parent&gt;&lt;comment/&gt;&lt;compiled_snapshot&gt;a8658136db6c2010969430d868961966&lt;/compiled_snapshot&gt;&lt;display_text/&gt;&lt;flow display_value="Test Subflow 2"&gt;0ebeb4bedb2c2010969430d868961914&lt;/flow&gt;&lt;order&gt;2&lt;/order&gt;&lt;parent_ui_id/&gt;&lt;sys_class_name&gt;sys_hub_action_instance&lt;/sys_class_name&gt;&lt;sys_created_by&gt;admin&lt;/sys_created_by&gt;&lt;sys_created_on&gt;2020-11-21 17:59:46&lt;/sys_created_on&gt;&lt;sys_id&gt;b9a58536db6c2010969430d86896198c&lt;/sys_id&gt;&lt;sys_mod_count&gt;4&lt;/sys_mod_count&gt;&lt;sys_scope display_value="Ethereum"&gt;3c0e4434db442010969430d868961918&lt;/sys_scope&gt;&lt;sys_updated_by&gt;admin&lt;/sys_updated_by&gt;&lt;sys_updated_on&gt;2020-11-21 17:59:46&lt;/sys_updated_on&gt;&lt;ui_id&gt;1356c76a-ba69-4f7b-b5cb-c0fad77117ad&lt;/ui_id&gt;&lt;/sys_hub_action_instance&gt;&lt;sys_variable_value action="delete_multiple" query="document_key=b9a58536db6c2010969430d86896198c"/&gt;&lt;sys_element_mapping action="delete_multiple" query="id=b9a58536db6c2010969430d86896198c"/&gt;&lt;sys_element_mapping action="INSERT_OR_UPDATE"&gt;&lt;field&gt;endpoint&lt;/field&gt;&lt;id&gt;b9a58536db6c2010969430d86896198c&lt;/id&gt;&lt;sys_created_by&gt;admin&lt;/sys_created_by&gt;&lt;sys_created_on&gt;2020-11-21 17:59:46&lt;/sys_created_on&gt;&lt;sys_id&gt;79a58536db6c2010969430d86896198d&lt;/sys_id&gt;&lt;sys_mod_count&gt;0&lt;/sys_mod_count&gt;&lt;sys_updated_by&gt;admin&lt;/sys_updated_by&gt;&lt;sys_updated_on&gt;2020-11-21 17:59:46&lt;/sys_updated_on&gt;&lt;table&gt;var__m_sys_hub_action_input_a8658136db6c2010969430d868961966&lt;/table&gt;&lt;value&gt;{{aece5707-e790-4ab3-87e5-338f0e5b9beb.endpoint}}&lt;/value&gt;&lt;/sys_element_mapping&gt;&lt;sys_element_mapping action="INSERT_OR_UPDATE"&gt;&lt;field&gt;key&lt;/field&gt;&lt;id&gt;b9a58536db6c2010969430d86896198c&lt;/id&gt;&lt;sys_created_by&gt;admin&lt;/sys_created_by&gt;&lt;sys_created_on&gt;2020-11-21 17:59:46&lt;/sys_created_on&gt;&lt;sys_id&gt;3da58536db6c2010969430d86896198d&lt;/sys_id&gt;&lt;sys_mod_count&gt;0&lt;/sys_mod_count&gt;&lt;sys_updated_by&gt;admin&lt;/sys_updated_by&gt;&lt;sys_updated_on&gt;2020-11-21 17:59:46&lt;/sys_updated_on&gt;&lt;table&gt;var__m_sys_hub_action_input_a8658136db6c2010969430d868961966&lt;/table&gt;&lt;value&gt;{{subflow.account.key}}&lt;/value&gt;&lt;/sys_element_mapping&gt;&lt;sys_flow_cat_variable_model action="delete_multiple" query="id=0ebeb4bedb2c2010969430d868961914^sys_idNOT IN02beb4bedb2c2010969430d868961915"/&gt;&lt;sys_flow_cat_variable_model action="INSERT_OR_UPDATE"&gt;&lt;id&gt;0ebeb4bedb2c2010969430d868961914&lt;/id&gt;&lt;name&gt;Test Subflow 2&lt;/name&gt;&lt;sys_created_by&gt;admin&lt;/sys_created_by&gt;&lt;sys_created_on&gt;2020-11-21 17:29:29&lt;/sys_created_on&gt;&lt;sys_id&gt;02beb4bedb2c2010969430d868961915&lt;/sys_id&gt;&lt;sys_mod_count&gt;0&lt;/sys_mod_count&gt;&lt;sys_scope/&gt;&lt;sys_updated_by&gt;admin&lt;/sys_updated_by&gt;&lt;sys_updated_on&gt;2020-11-21 17:29:29&lt;/sys_updated_on&gt;&lt;/sys_flow_cat_variable_model&gt;&lt;sys_hub_flow_input action="delete_multiple" query="model=0ebeb4bedb2c2010969430d868961914^sys_idNOT IN1d9485f2db6c2010969430d86896199d,cebeb4bedb2c2010969430d868961915"/&gt;&lt;sys_hub_flow_input action="INSERT_OR_UPDATE"&gt;&lt;active&gt;true&lt;/active&gt;&lt;array&gt;false&lt;/array&gt;&lt;array_denormalized&gt;false&lt;/array_denormalized&gt;&lt;attributes&gt;element_mapping_provider=com.glide.flow_design.action.data.FlowDesignVariableMapper,uiType=reference,uiTypeLabel=Reference,uiUniqueId=8bc7b41a-4665-4dad-8beb-e207993798f2&lt;/attributes&gt;&lt;audit&gt;false&lt;/audit&gt;&lt;calculation&gt;&lt;![CDATA[(function calculatedFieldValue(current) {

	// Add your code here
	return '';  // return the calculated value

})(current);]]&gt;&lt;/calculation&gt;&lt;choice/&gt;&lt;choice_field/&gt;&lt;choice_table&gt;x_snc_ethsign_account&lt;/choice_table&gt;&lt;column_label/&gt;&lt;comments/&gt;&lt;create_roles/&gt;&lt;default_value/&gt;&lt;defaultsort/&gt;&lt;delete_roles/&gt;&lt;dependent/&gt;&lt;dependent_on_field/&gt;&lt;display&gt;false&lt;/display&gt;&lt;dynamic_creation&gt;false&lt;/dynamic_creation&gt;&lt;dynamic_creation_script/&gt;&lt;dynamic_default_value/&gt;&lt;dynamic_ref_qual/&gt;&lt;element&gt;account&lt;/element&gt;&lt;element_reference&gt;false&lt;/element_reference&gt;&lt;foreign_database/&gt;&lt;function_definition/&gt;&lt;function_field&gt;false&lt;/function_field&gt;&lt;help/&gt;&lt;hint/&gt;&lt;internal_type display_value="Reference"&gt;reference&lt;/internal_type&gt;&lt;label&gt;account&lt;/label&gt;&lt;mandatory&gt;true&lt;/mandatory&gt;&lt;max_length&gt;32&lt;/max_length&gt;&lt;model display_value="Test Subflow 2"&gt;0ebeb4bedb2c2010969430d868961914&lt;/model&gt;&lt;model_id&gt;0ebeb4bedb2c2010969430d868961914&lt;/model_id&gt;&lt;model_table&gt;sys_hub_flow_snapshot&lt;/model_table&gt;&lt;name&gt;var__m_sys_hub_flow_input_0ebeb4bedb2c2010969430d868961914&lt;/name&gt;&lt;next_element/&gt;&lt;order&gt;2&lt;/order&gt;&lt;primary&gt;false&lt;/primary&gt;&lt;read_only&gt;false&lt;/read_only&gt;&lt;read_roles/&gt;&lt;reference display_value="" name="x_snc_ethsign_account"&gt;x_snc_ethsign_account&lt;/reference&gt;&lt;reference_cascade_rule/&gt;&lt;reference_floats&gt;false&lt;/reference_floats&gt;&lt;reference_key/&gt;&lt;reference_qual/&gt;&lt;reference_qual_condition/&gt;&lt;reference_type/&gt;&lt;sizeclass/&gt;&lt;spell_check&gt;false&lt;/spell_check&gt;&lt;staged&gt;false&lt;/staged&gt;&lt;sys_class_name&gt;sys_hub_flow_input&lt;/sys_class_name&gt;&lt;sys_created_by&gt;admin&lt;/sys_created_by&gt;&lt;sys_created_on&gt;2020-11-21 17:55:06&lt;/sys_created_on&gt;&lt;sys_id&gt;1d9485f2db6c2010969430d86896199d&lt;/sys_id&gt;&lt;sys_mod_count&gt;1&lt;/sys_mod_count&gt;&lt;sys_name/&gt;&lt;sys_package/&gt;&lt;sys_policy/&gt;&lt;sys_scope display_value="Ethereum"&gt;3c0e4434db442010969430d868961918&lt;/sys_scope&gt;&lt;sys_update_name/&gt;&lt;sys_updated_by&gt;admin&lt;/sys_updated_by&gt;&lt;sys_updated_on&gt;2020-11-21 17:55:06&lt;/sys_updated_on&gt;&lt;table_reference&gt;false&lt;/table_reference&gt;&lt;text_index&gt;false&lt;/text_index&gt;&lt;unique&gt;false&lt;/unique&gt;&lt;use_dependent_field&gt;false&lt;/use_dependent_field&gt;&lt;use_dynamic_default&gt;false&lt;/use_dynamic_default&gt;&lt;use_reference_qualifier&gt;simple&lt;/use_reference_qualifier&gt;&lt;virtual&gt;false&lt;/virtual&gt;&lt;widget/&gt;&lt;write_roles/&gt;&lt;xml_view&gt;false&lt;/xml_view&gt;&lt;/sys_hub_flow_input&gt;&lt;sys_hub_flow_input action="INSERT_OR_UPDATE"&gt;&lt;active&gt;true&lt;/active&gt;&lt;array&gt;false&lt;/array&gt;&lt;array_denormalized&gt;false&lt;/array_denormalized&gt;&lt;attributes&gt;element_mapping_provider=com.glide.flow_design.action.data.FlowDesignVariableMapper,uiType=reference,uiTypeLabel=Reference,uiUniqueId=3597a85b-fa8e-468d-a286-e2fcbb81eddf&lt;/attributes&gt;&lt;audit&gt;false&lt;/audit&gt;&lt;calculation&gt;&lt;![CDATA[(function calculatedFieldValue(current) {

	// Add your code here
	return '';  // return the calculated value

})(current);]]&gt;&lt;/calculation&gt;&lt;choice/&gt;&lt;choice_field/&gt;&lt;choice_table&gt;x_snc_ethereum_network&lt;/choice_table&gt;&lt;column_label/&gt;&lt;comments/&gt;&lt;create_roles/&gt;&lt;default_value/&gt;&lt;defaultsort/&gt;&lt;delete_roles/&gt;&lt;dependent/&gt;&lt;dependent_on_field/&gt;&lt;display&gt;false&lt;/display&gt;&lt;dynamic_creation&gt;false&lt;/dynamic_creation&gt;&lt;dynamic_creation_script/&gt;&lt;dynamic_default_value/&gt;&lt;dynamic_ref_qual/&gt;&lt;element&gt;network&lt;/element&gt;&lt;element_reference&gt;false&lt;/element_reference&gt;&lt;foreign_database/&gt;&lt;function_definition/&gt;&lt;function_field&gt;false&lt;/function_field&gt;&lt;help/&gt;&lt;hint/&gt;&lt;internal_type display_value="Reference"&gt;reference&lt;/internal_type&gt;&lt;label&gt;network&lt;/label&gt;&lt;mandatory&gt;true&lt;/mandatory&gt;&lt;max_length&gt;32&lt;/max_length&gt;&lt;model display_value="Test Subflow 2"&gt;0ebeb4bedb2c2010969430d868961914&lt;/model&gt;&lt;model_id&gt;0ebeb4bedb2c2010969430d868961914&lt;/model_id&gt;&lt;model_table&gt;sys_hub_flow_snapshot&lt;/model_table&gt;&lt;name&gt;var__m_sys_hub_flow_input_0ebeb4bedb2c2010969430d868961914&lt;/name&gt;&lt;next_element/&gt;&lt;order&gt;1&lt;/order&gt;&lt;primary&gt;false&lt;/primary&gt;&lt;read_only&gt;false&lt;/read_only&gt;&lt;read_roles/&gt;&lt;reference display_value="" name="x_snc_ethereum_network"&gt;x_snc_ethereum_network&lt;/reference&gt;&lt;reference_cascade_rule/&gt;&lt;reference_floats&gt;false&lt;/reference_floats&gt;&lt;reference_key/&gt;&lt;reference_qual/&gt;&lt;reference_qual_condition/&gt;&lt;reference_type/&gt;&lt;sizeclass/&gt;&lt;spell_check&gt;false&lt;/spell_check&gt;&lt;staged&gt;false&lt;/staged&gt;&lt;sys_class_name&gt;sys_hub_flow_input&lt;/sys_class_name&gt;&lt;sys_created_by&gt;admin&lt;/sys_created_by&gt;&lt;sys_created_on&gt;2020-11-21 17:29:29&lt;/sys_created_on&gt;&lt;sys_id&gt;cebeb4bedb2c2010969430d868961915&lt;/sys_id&gt;&lt;sys_mod_count&gt;1&lt;/sys_mod_count&gt;&lt;sys_name/&gt;&lt;sys_package/&gt;&lt;sys_policy/&gt;&lt;sys_scope display_value="Ethereum"&gt;3c0e4434db442010969430d868961918&lt;/sys_scope&gt;&lt;sys_update_name/&gt;&lt;sys_updated_by&gt;admin&lt;/sys_updated_by&gt;&lt;sys_updated_on&gt;2020-11-21 17:29:29&lt;/sys_updated_on&gt;&lt;table_reference&gt;false&lt;/table_reference&gt;&lt;text_index&gt;false&lt;/text_index&gt;&lt;unique&gt;false&lt;/unique&gt;&lt;use_dependent_field&gt;false&lt;/use_dependent_field&gt;&lt;use_dynamic_default&gt;false&lt;/use_dynamic_default&gt;&lt;use_reference_qualifier&gt;simple&lt;/use_reference_qualifier&gt;&lt;virtual&gt;false&lt;/virtual&gt;&lt;widget/&gt;&lt;write_roles/&gt;&lt;xml_view&gt;false&lt;/xml_view&gt;&lt;/sys_hub_flow_input&gt;&lt;sys_hub_action_instance action="delete_multiple" query="flow=0ebeb4bedb2c2010969430d868961914^sys_idNOT IN16beb4bedb2c2010969430d868961932,b9a58536db6c2010969430d86896198c"/&gt;&lt;sys_hub_action_instance action="INSERT_OR_UPDATE"&gt;&lt;action_inputs/&gt;&lt;action_inputs/&gt;&lt;action_type display_value="Identify Endpoint"&gt;1643eb16db602010969430d868961947&lt;/action_type&gt;&lt;action_type_parent display_value="Identify Endpoint"&gt;07b22716db602010969430d868961946&lt;/action_type_parent&gt;&lt;comment/&gt;&lt;compiled_snapshot&gt;1643eb16db602010969430d868961947&lt;/compiled_snapshot&gt;&lt;display_text/&gt;&lt;flow display_value="Test Subflow 2"&gt;0ebeb4bedb2c2010969430d868961914&lt;/flow&gt;&lt;order&gt;1&lt;/order&gt;&lt;parent_ui_id/&gt;&lt;sys_class_name&gt;sys_hub_action_instance&lt;/sys_class_name&gt;&lt;sys_created_by&gt;admin&lt;/sys_created_by&gt;&lt;sys_created_on&gt;2020-11-21 17:29:29&lt;/sys_created_on&gt;&lt;sys_id&gt;16beb4bedb2c2010969430d868961932&lt;/sys_id&gt;&lt;sys_mod_count&gt;10&lt;/sys_mod_count&gt;&lt;sys_scope display_value="Ethereum"&gt;3c0e4434db442010969430d868961918&lt;/sys_scope&gt;&lt;sys_updated_by&gt;admin&lt;/sys_updated_by&gt;&lt;sys_updated_on&gt;2020-11-21 17:59:46&lt;/sys_updated_on&gt;&lt;ui_id&gt;aece5707-e790-4ab3-87e5-338f0e5b9beb&lt;/ui_id&gt;&lt;/sys_hub_action_instance&gt;&lt;sys_variable_value action="delete_multiple" query="document_key=16beb4bedb2c2010969430d868961932"/&gt;&lt;sys_element_mapping action="delete_multiple" query="id=16beb4bedb2c2010969430d868961932"/&gt;&lt;sys_element_mapping action="INSERT_OR_UPDATE"&gt;&lt;field&gt;network&lt;/field&gt;&lt;id&gt;16beb4bedb2c2010969430d868961932&lt;/id&gt;&lt;sys_created_by&gt;admin&lt;/sys_created_by&gt;&lt;sys_created_on&gt;2020-11-21 17:29:29&lt;/sys_created_on&gt;&lt;sys_id&gt;52beb4bedb2c2010969430d868961933&lt;/sys_id&gt;&lt;sys_mod_count&gt;0&lt;/sys_mod_count&gt;&lt;sys_updated_by&gt;admin&lt;/sys_updated_by&gt;&lt;sys_updated_on&gt;2020-11-21 17:29:29&lt;/sys_updated_on&gt;&lt;table&gt;var__m_sys_hub_action_input_1643eb16db602010969430d868961947&lt;/table&gt;&lt;value&gt;{{subflow.network}}&lt;/value&gt;&lt;/sys_element_mapping&gt;&lt;sys_hub_action_instance action="INSERT_OR_UPDATE"&gt;&lt;action_inputs/&gt;&lt;action_inputs/&gt;&lt;action_type display_value="Copy of Define Nonce"&gt;a8658136db6c2010969430d868961966&lt;/action_type&gt;&lt;action_type_parent display_value="Copy of Define Nonce"&gt;8345cdf2db6c2010969430d8689619d9&lt;/action_type_parent&gt;&lt;comment/&gt;&lt;compiled_snapshot&gt;a8658136db6c2010969430d868961966&lt;/compiled_snapshot&gt;&lt;display_text/&gt;&lt;flow display_value="Test Subflow 2"&gt;0ebeb4bedb2c2010969430d868961914&lt;/flow&gt;&lt;order&gt;2&lt;/order&gt;&lt;parent_ui_id/&gt;&lt;sys_class_name&gt;sys_hub_action_instance&lt;/sys_class_name&gt;&lt;sys_created_by&gt;admin&lt;/sys_created_by&gt;&lt;sys_created_on&gt;2020-11-21 17:59:46&lt;/sys_created_on&gt;&lt;sys_id&gt;b9a58536db6c2010969430d86896198c&lt;/sys_id&gt;&lt;sys_mod_count&gt;4&lt;/sys_mod_count&gt;&lt;sys_scope display_value="Ethereum"&gt;3c0e4434db442010969430d868961918&lt;/sys_scope&gt;&lt;sys_updated_by&gt;admin&lt;/sys_updated_by&gt;&lt;sys_updated_on&gt;2020-11-21 17:59:46&lt;/sys_updated_on&gt;&lt;ui_id&gt;1356c76a-ba69-4f7b-b5cb-c0fad77117ad&lt;/ui_id&gt;&lt;/sys_hub_action_instance&gt;&lt;sys_variable_value action="delete_multiple" query="document_key=b9a58536db6c2010969430d86896198c"/&gt;&lt;sys_element_mapping action="delete_multiple" query="id=b9a58536db6c2010969430d86896198c"/&gt;&lt;sys_element_mapping action="INSERT_OR_UPDATE"&gt;&lt;field&gt;endpoint&lt;/field&gt;&lt;id&gt;b9a58536db6c2010969430d86896198c&lt;/id&gt;&lt;sys_created_by&gt;admin&lt;/sys_created_by&gt;&lt;sys_created_on&gt;2020-11-21 17:59:46&lt;/sys_created_on&gt;&lt;sys_id&gt;79a58536db6c2010969430d86896198d&lt;/sys_id&gt;&lt;sys_mod_count&gt;0&lt;/sys_mod_count&gt;&lt;sys_updated_by&gt;admin&lt;/sys_updated_by&gt;&lt;sys_updated_on&gt;2020-11-21 17:59:46&lt;/sys_updated_on&gt;&lt;table&gt;var__m_sys_hub_action_input_a8658136db6c2010969430d868961966&lt;/table&gt;&lt;value&gt;{{aece5707-e790-4ab3-87e5-338f0e5b9beb.endpoint}}&lt;/value&gt;&lt;/sys_element_mapping&gt;&lt;sys_element_mapping action="INSERT_OR_UPDATE"&gt;&lt;field&gt;key&lt;/field&gt;&lt;id&gt;b9a58536db6c2010969430d86896198c&lt;/id&gt;&lt;sys_created_by&gt;admin&lt;/sys_created_by&gt;&lt;sys_created_on&gt;2020-11-21 17:59:46&lt;/sys_created_on&gt;&lt;sys_id&gt;3da58536db6c2010969430d86896198d&lt;/sys_id&gt;&lt;sys_mod_count&gt;0&lt;/sys_mod_count&gt;&lt;sys_updated_by&gt;admin&lt;/sys_updated_by&gt;&lt;sys_updated_on&gt;2020-11-21 17:59:46&lt;/sys_updated_on&gt;&lt;table&gt;var__m_sys_hub_action_input_a8658136db6c2010969430d868961966&lt;/table&gt;&lt;value&gt;{{subflow.account.key}}&lt;/value&gt;&lt;/sys_element_mapping&gt;&lt;sys_documentation action="delete_multiple" query="name=var__m_sys_hub_flow_input_0ebeb4bedb2c2010969430d868961914^sys_idNOT IN1ebeb4bedb2c2010969430d86896191c,a19485f2db6c2010969430d8689619a5"/&gt;&lt;sys_documentation action="INSERT_OR_UPDATE"&gt;&lt;element&gt;network&lt;/element&gt;&lt;help/&gt;&lt;hint/&gt;&lt;label&gt;network&lt;/label&gt;&lt;language&gt;en&lt;/language&gt;&lt;name&gt;var__m_sys_hub_flow_input_0ebeb4bedb2c2010969430d868961914&lt;/name&gt;&lt;plural/&gt;&lt;sys_class_name&gt;sys_documentation&lt;/sys_class_name&gt;&lt;sys_created_by&gt;admin&lt;/sys_created_by&gt;&lt;sys_created_on&gt;2020-11-21 17:29:29&lt;/sys_created_on&gt;&lt;sys_id&gt;1ebeb4bedb2c2010969430d86896191c&lt;/sys_id&gt;&lt;sys_mod_count&gt;0&lt;/sys_mod_count&gt;&lt;sys_name/&gt;&lt;sys_package display_value="Ethereum" source="x_snc_ethereum"&gt;3c0e4434db442010969430d868961918&lt;/sys_package&gt;&lt;sys_policy/&gt;&lt;sys_scope display_value="Ethereum"&gt;3c0e4434db442010969430d868961918&lt;/sys_scope&gt;&lt;sys_update_name/&gt;&lt;sys_updated_by&gt;admin&lt;/sys_updated_by&gt;&lt;sys_updated_on&gt;2020-11-21 17:29:29&lt;/sys_updated_on&gt;&lt;url/&gt;&lt;url_target/&gt;&lt;/sys_documentation&gt;&lt;sys_documentation action="INSERT_OR_UPDATE"&gt;&lt;element&gt;account&lt;/element&gt;&lt;help/&gt;&lt;hint/&gt;&lt;label&gt;account&lt;/label&gt;&lt;language&gt;en&lt;/language&gt;&lt;name&gt;var__m_sys_hub_flow_input_0ebeb4bedb2c2010969430d868961914&lt;/name&gt;&lt;plural/&gt;&lt;sys_class_name&gt;sys_documentation&lt;/sys_class_name&gt;&lt;sys_created_by&gt;admin&lt;/sys_created_by&gt;&lt;sys_created_on&gt;2020-11-21 17:55:06&lt;/sys_created_on&gt;&lt;sys_id&gt;a19485f2db6c2010969430d8689619a5&lt;/sys_id&gt;&lt;sys_mod_count&gt;0&lt;/sys_mod_count&gt;&lt;sys_name/&gt;&lt;sys_package display_value="Ethereum" source="x_snc_ethereum"&gt;3c0e4434db442010969430d868961918&lt;/sys_package&gt;&lt;sys_policy/&gt;&lt;sys_scope display_value="Ethereum"&gt;3c0e4434db442010969430d868961918&lt;/sys_scope&gt;&lt;sys_update_name/&gt;&lt;sys_updated_by&gt;admin&lt;/sys_updated_by&gt;&lt;sys_updated_on&gt;2020-11-21 17:55:06&lt;/sys_updated_on&gt;&lt;url/&gt;&lt;url_target/&gt;&lt;/sys_documentation&gt;&lt;/record_update&gt;</payload>
        <payload_hash>2085232508</payload_hash>
        <record_name>Test Subflow 2</record_name>
        <reverted_from/>
        <source>4b37ad4e1ba0a81064bf11fc2d4bcbfa</source>
        <source_table>sys_update_set</source_table>
        <state>previous</state>
        <sys_created_by>admin</sys_created_by>
        <sys_created_on>2020-11-21 17:59:49</sys_created_on>
        <sys_id>12a58536db6c2010969430d8689619f9</sys_id>
        <sys_mod_count>0</sys_mod_count>
        <sys_recorded_at>175ebf64e1a0000001</sys_recorded_at>
        <sys_updated_by>admin</sys_updated_by>
        <sys_updated_on>2020-11-21 17:59:49</sys_updated_on>
        <type>Flow</type>
        <update_guid>1aa585364d6c20106a5243ddc8c75bf8</update_guid>
        <update_guid_history>1aa585364d6c20106a5243ddc8c75bf8:2085232508,61a58536a06c20104cb0acdc731e4758:-1680654150,44a585364d6c2010b9c3771da05a8802:285642810,6294c5f2e46c201098fa94dbf85a8a42:-1397446967,1d9485f2166c2010ab2b18d860c6c171:1351772371,5b92c172f86c20104d06b1885b197a79:92926675,57420172dc6c20109d66453fd8123f16:-2068962388,32beb4be632c201029c627083bf9fa96:624253515,8ebeb4bea92c2010ff90e7342a5a990b:1508010420,77ed3c7ea72c2010eb5e75690e49ce7b:534921524,857db47e622c2010877f08ee36d63ccd:-601616022</update_guid_history>
    </sys_update_version>
    <sys_metadata_delete action="INSERT_OR_UPDATE">
        <sys_audit_delete/>
        <sys_class_name>sys_metadata_delete</sys_class_name>
        <sys_created_by>admin</sys_created_by>
        <sys_created_on>2020-11-25 17:17:40</sys_created_on>
        <sys_db_object display_value="" name="sys_hub_flow">sys_hub_flow</sys_db_object>
        <sys_id>3ae2be870682480093eb7733e4436101</sys_id>
        <sys_metadata>c57db47edb2c2010969430d8689619c7</sys_metadata>
        <sys_mod_count>0</sys_mod_count>
        <sys_name>Test Subflow 2</sys_name>
        <sys_package display_value="Ethereum" source="x_snc_ethereum">3c0e4434db442010969430d868961918</sys_package>
        <sys_parent/>
        <sys_policy/>
        <sys_scope display_value="Ethereum">3c0e4434db442010969430d868961918</sys_scope>
        <sys_scope_delete display_value="">2bb8a3046e8a400e969b229d381b21b1</sys_scope_delete>
        <sys_update_name>sys_hub_flow_c57db47edb2c2010969430d8689619c7</sys_update_name>
        <sys_update_version display_value="sys_hub_flow_c57db47edb2c2010969430d8689619c7">12a58536db6c2010969430d8689619f9</sys_update_version>
        <sys_updated_by>admin</sys_updated_by>
        <sys_updated_on>2020-11-25 17:17:40</sys_updated_on>
    </sys_metadata_delete>
</record_update>
